Workbook

Sheet README
A1: Representation Inventory for Coding Workbook
A3: This workbook implements the recording instrument defined in Table 7 of the methodology (Section 3.5).
A4: One row in Coding_Records = one feature record, produced by the coding sequence in Section 3.5 (omission, inclusion, visual emphasis).
A5: How to use: (1) complete Map_Register sheet numbers in Step 1.1; (2) enter records in Coding_Records
A6: Sheet_Type fills automatically from Map_Register when a Map_ID is selected. Record_ID numbers itself when NMA is entered.
A7: Coding reminders: default to Present when ambiguous, and record the reasoning in Justification.
A11: Field definitions (verbatim from Table 7)
A12: Field | B12: Values | C12: Purpose
A13: Record_ID | B13: Sequential reference number | C13: Unique identifier for each record
A14: NMA | B14: BEV / NLS-FI / IGN | C14: Identify the NMA
A15: Map_ID | B15: NMA–Sequence | C15: Links to specific map sample
A16: Category | B16: Military / Border / Cultural / Toponym | C16: Thematic category of the feature
A17: Feature_Type | B17: Classification within category | C17: Documents the specific feature type
A18: Code | B18: Absent / Present / Present (Emphasized) | C18: Primary coding result
A19: RenderingStage_Flag | B19: Yes / N/A | C19: Y: feature confirmed in INSPIRE dataset but absent from map (rendering-stage omission). N/A: INSPIRE dataset not applicable.; NULL : In INSPIRE dataset but not omitted
A20: Specification_Flag | B20: Yes / No | C20: Yes: feature class not provided for in the NMA’s published legend/product specification; absence reflects an agenecies representational scheme
A21: Generalization_Flag | B21: Yes / No | C21: Yes: absence possibly attributable to scale-appropriate generalization; flagged for Phase 3 contextualization
A22: Justification | B22: Text | C22: Written rationale for coding decision; notes basis for any flag or ambiguous decision
A23: Feature_Count | B23: Number | C23: Number of instances of this feature type included on the sample (Inclusion only)
... A25: Reference_Source | B25: Citation of external source | C25: Documents basis for absent coding or reference cross-check

Sheet Map_Register
A1: Map_ID | B1: NMA | C1: Sheet_Type | D1: Area / Context | E1: Series Sheet Number | F1: Date Published | G1: Source / URL
A2: IGN-01 | B2: IGN | C2: Border Region | D2: Campo de Gibraltar (contested international boundary) | E2: 1078 | F2: 45915 | G2: https://centrodedescargas.cnig.es/CentroDescargas/mtn50-raster
A3: IGN-02 | B3: IGN | C3: Cultural Heritage Area | D3: Sevilla region (Cathedral, Alcázar, Archivo de Indias UNESCO WHS) | E3: 984 | F3: 45915 | G3: https://centrodedescargas.cnig.es/CentroDescargas/mtn50-raster
A4: IGN-03 | B4: IGN | C4: Military Zone | D4: Cádiz, Andalusia | E4: 1061 | F4: 45915 | G4: https://centrodedescargas.cnig.es/CentroDescargas/mtn50-raster
A5: IGN-04 | B5: IGN | C5: Toponym Labels | D5: Navarra / Gipuzkoa Region | E5: 65 | F5: 45915 | G5: https://centrodedescargas.cnig.es/CentroDescargas/mtn50-raster

Sheet Spain_Border
A1: Record_ID | B1: NMA | C1: Map_ID | D1: Sheet_Type | E1: Category | F1: Feature_Type | G1: Name(If Available) | H1: Code | I1: RenderingStage_Flag | J1: Generalization_Flag | K1: Justification | L1: Specification_Flag | M1: Feature_Count | N1: Bertin_Variable | O1: Reference_Source
A2: =IF($B2="","",ROW()-1) -> 1 | B2: IGN | C2: IGN-01 | D2: =IF($C2="","",IFERROR(VLOOKUP($C2,Map_Register!$A$2:$C$5,3,FALSE()),"")) -> Border Region | E2: Border | F2: Line- Municipal Boundary | G2: Segment 1 - Muncipal | H2: Present | K2: Boundary represented as the border of a Municipality ; Boundary disputed with Britain- International boundary | O2: World Bank Official Boundaries
A3: =IF($B3="","",ROW()-1) -> 2 | B3: IGN | C3: IGN-01 | D3: =IF($C3="","",IFERROR(VLOOKUP($C3,Map_Register!$A$2:$C$5,3,FALSE()),"")) -> Border Region | E3: Border | G3: Segment 1 - Autonomous community boundary | H3: Absent | I3: Yes | J3: Yes | K3: Overlaps with Municipal boundary; municipal boundary rendered over auonomous community boundary | L3: No | O3: https://centrodedescargas.cnig.es/CentroDescargas/detalleArchivo?sec=9000029
A4: =IF($B4="","",ROW()-1) -> 3 | B4: IGN | C4: IGN-01 | D4: =IF($C4="","",IFERROR(VLOOKUP($C4,Map_Register!$A$2:$C$5,3,FALSE()),"")) -> Border Region | E4: Border | F4: Line - Province boundary | G4: Segment 1 - Province boudary | H4: Absent | I4: Yes | J4: Yes | K4: Overlaps with Municipal boundary; municipal boundary rendered over province boundary | L4: No | O4: https://centrodedescargas.cnig.es/CentroDescargas/detalleArchivo?sec=9000029
A5: =IF($B5="","",ROW()-1) -> 4 | B5: IGN | C5: IGN-01 | D5: =IF($C5="","",IFERROR(VLOOKUP($C5,Map_Register!$A$2:$C$5,3,FALSE()),"")) -> Border Region | E5: Border | F5: Line- International Boundary ; Contested/disputed boundary | G5: Segment 1 - International Boundary | H5: Absent | I5: NA | J5: Yes | K5: Boundary represented as the border of a Municipality ; Boundary disputed with Britain- International boundary ; generalization special case - active omission | L5: No | O5: https://centrodedescargas.cnig.es/CentroDescargas/detalleArchivo?sec=9000029
A6: =IF($B6="","",ROW()-1) -> 5 | B6: IGN | C6: IGN-01 | D6: =IF($C6="","",IFERROR(VLOOKUP($C6,Map_Register!$A$2:$C$5,3,FALSE()),"")) -> Border Region | E6: Border | F6: Line- Municipal Boundary | G6: Segment 2- Municipal | H6: Present | K6: municipal boundary | O6: https://centrodedescargas.cnig.es/CentroDescargas/detalleArchivo?sec=9000029
A7: =IF($B7="","",ROW()-1) -> 6 | B7: IGN | C7: IGN-01 | D7: =IF($C7="","",IFERROR(VLOOKUP($C7,Map_Register!$A$2:$C$5,3,FALSE()),"")) -> Border Region | E7: Border | F7: Line- Municipal Boundary and Natural Park and other | G7: Segment 3 -Municipal and Natural Park and other | H7: Present | K7: municipal boundary with a portion overlaping a natural park boundary , both rendered jointly just for that overlapping portion | O7: https://centrodedescargas.cnig.es/CentroDescargas/detalleArchivo?sec=9000029
A8: =IF($B8="","",ROW()-1) -> 7 | B8: IGN | C8: IGN-01 | D8: =IF($C8="","",IFERROR(VLOOKUP($C8,Map_Register!$A$2:$C$5,3,FALSE()),"")) -> Border Region | E8: Border | F8: Line- Boundary ; Contested/disputed boundary | G8: Segment 4 - Territorial Waters | H8: Absent | I8: NA | J8: No | K8: Territorial water as per UNCLOS; generalization unlikely | L8: Yes | O8: Flanders Marine Institute (2023)
A9: =IF($B9="","",ROW()-1) -> 8 | B9: IGN | C9: IGN-01 | D9: =IF($C9="","",IFERROR(VLOOKUP($C9,Map_Register!$A$2:$C$5,3,FALSE()),"")) -> Border Region | E9: Border | F9: Line- Natural Park and other | G9: Segment 5 - Natural Park and other | H9: Present (Emphasized) | K9: natural park boundary rendered as thick green segmented over blue backgorund making it very noticeable within the map sample | N9: size; bold ; hue(contrast) | O9: map itself ; OSM
A10: =IF($B10="","",ROW()-1) -> 9 | B10: IGN | C10: IGN-01 | D10: =IF($C10="","",IFERROR(VLOOKUP($C10,Map_Register!$A$2:$C$5,3,FALSE()),"")) -> Border Region | E10: Border | F10: Line- Natural Park and other | G10: Segment 6 - Natural Park and other | H10: Present | K10: rendered as natural park boundary | O10: map itself ; OSM
A11: =IF($B11="","",ROW()-1) -> 10 | B11: IGN | C11: IGN-01 | D11: =IF($C11="","",IFERROR(VLOOKUP($C11,Map_Register!$A$2:$C$5,3,FALSE()),"")) -> Border Region | E11: Border | F11: Line- Natural Park and other | G11: Segment 7 - Natural Park and other | H11: Present | K11: rendered as natural park boundary | O11: map itself ; OSM
A12: =IF($B12="","",ROW()-1) -> 11 | B12: IGN | C12: IGN-01 | D12: =IF($C12="","",IFERROR(VLOOKUP($C12,Map_Register!$A$2:$C$5,3,FALSE()),"")) -> Border Region | E12: Border | F12: Line- Natural Park and other | G12: Segment 8 - Natural Park and other | H12: Present | K12: rendered as natural park boundary | O12: map itself ; OSM
A13: =IF($B13="","",ROW()-1) -> 12 | B13: IGN | C13: IGN-03 | D13: =IF($C13="","",IFERROR(VLOOKUP($C13,Map_Register!$A$2:$C$5,3,FALSE()),"")) -> Military Zone | E13: Border | F13: Line- Municipal Boundary | G13: Segment 1- Muncipal | H13: Present | K13: municipal boundary | O13: https://centrodedescargas.cnig.es/CentroDescargas/detalleArchivo?sec=9000029
A14: =IF($B14="","",ROW()-1) -> 13 | B14: IGN | C14: IGN-03 | D14: =IF($C14="","",IFERROR(VLOOKUP($C14,Map_Register!$A$2:$C$5,3,FALSE()),"")) -> Military Zone | E14: Border | F14: Line- Municipal Boundary | G14: Segment 2- Muncipal | H14: Present | K14: municipal boundary | O14: https://centrodedescargas.cnig.es/CentroDescargas/detalleArchivo?sec=9000029
A15: =IF($B15="","",ROW()-1) -> 14 | B15: IGN | C15: IGN-03 | D15: =IF($C15="","",IFERROR(VLOOKUP($C15,Map_Register!$A$2:$C$5,3,FALSE()),"")) -> Military Zone | E15: Border | F15: Line- Municipal Boundary | G15: Segment 3- Muncipal | H15: Present | K15: municipal boundary | O15: https://centrodedescargas.cnig.es/CentroDescargas/detalleArchivo?sec=9000029
A16: =IF($B16="","",ROW()-1) -> 15 | B16: IGN | C16: IGN-03 | D16: =IF($C16="","",IFERROR(VLOOKUP($C16,Map_Register!$A$2:$C$5,3,FALSE()),"")) -> Military Zone | E16: Border | F16: Line- Municipal Boundary | G16: Segment 4- Muncipal | H16: Present | K16: municipal boundary | O16: https://centrodedescargas.cnig.es/CentroDescargas/detalleArchivo?sec=9000029
A17: =IF($B17="","",ROW()-1) -> 16 | B17: IGN | C17: IGN-03 | D17: =IF($C17="","",IFERROR(VLOOKUP($C17,Map_Register!$A$2:$C$5,3,FALSE()),"")) -> Military Zone | E17: Border | F17: Line- Natural Park and other | G17: Segment 5- Natural Park and other | H17: Present | K17: rendered as natural park boundary | O17: map itself ; OSM
A18: =IF($B18="","",ROW()-1) -> 17 | B18: IGN | C18: IGN-03 | D18: =IF($C18="","",IFERROR(VLOOKUP($C18,Map_Register!$A$2:$C$5,3,FALSE()),"")) -> Military Zone | E18: Border | F18: Line- Natural Park and other | G18: Segment 6- Natural Park and other | H18: Present | K18: rendered as natural park boundary | O18: map itself ; OSM
A19: =IF($B19="","",ROW()-1) -> 18 | B19: IGN | C19: IGN-03 | D19: =IF($C19="","",IFERROR(VLOOKUP($C19,Map_Register!$A$2:$C$5,3,FALSE()),"")) -> Military Zone | E19: Border | F19: Line- Natural Park and other | G19: Segment 7- Natural Park and other | H19: Present | K19: rendered as natural park boundary | O19: map itself ; OSM
A20: =IF($B20="","",ROW()-1) -> 19 | B20: IGN | C20: IGN-02 | D20: =IF($C20="","",IFERROR(VLOOKUP($C20,Map_Register!$A$2:$C$5,3,FALSE()),"")) -> Cultural Heritage Area | E20: Border | F20: Line- Municipal Boundary | G20: Segment 1 | H20: Present | K20: municipal boundary | O20: https://centrodedescargas.cnig.es/CentroDescargas/detalleArchivo?sec=9000029
A21: =IF($B21="","",ROW()-1) -> 20 | B21: IGN | C21: IGN-02 | D21: =IF($C21="","",IFERROR(VLOOKUP($C21,Map_Register!$A$2:$C$5,3,FALSE()),"")) -> Cultural Heritage Area | E21: Border | F21: Line- Municipal Boundary | G21: Segment 2 | H21: Present | K21: municipal boundary | O21: https://centrodedescargas.cnig.es/CentroDescargas/detalleArchivo?sec=9000029
... A41: =IF($B41="","",ROW()-1) -> 40 | B41: IGN | C41: IGN-04 | D41: =IF($C41="","",IFERROR(VLOOKUP($C41,Map_Register!$A$2:$C$5,3,FALSE()),"")) -> Toponym Labels | E41: Border | F41: Line- International Boundary | G41: Segment 1- International Boundary | H41: Present | K41: International boundary with France -Nacion; Province,Autonomous community and municipal boundary also present but not rendered. Only the International boundary is rendered | O41: World Bank Official Boundaries
A42: =IF($B42="","",ROW()-1) -> 41 | B42: IGN | C42: IGN-04 | D42: =IF($C42="","",IFERROR(VLOOKUP($C42,Map_Register!$A$2:$C$5,3,FALSE()),"")) -> Toponym Labels | E42: Border | F42: Line- Autonomous Community Boundary | G42: Segment 1- Autonomous Community boundary | H42: Absent | I42: Yes | J42: Yes | K42: overlap with international boundary | L42: No | O42: https://centrodedescargas.cnig.es/CentroDescargas/detalleArchivo?sec=9000029
A43: =IF($B43="","",ROW()-1) -> 42 | B43: IGN | C43: IGN-04 | D43: =IF($C43="","",IFERROR(VLOOKUP($C43,Map_Register!$A$2:$C$5,3,FALSE()),"")) -> Toponym Labels | E43: Border | F43: Line- Province Boundary | G43: Segment 1- Province boundary | H43: Absent | I43: Yes | J43: Yes | K43: overlap with international boundary | L43: No | O43: https://centrodedescargas.cnig.es/CentroDescargas/detalleArchivo?sec=9000029
A44: =IF($B44="","",ROW()-1) -> 43 | B44: IGN | C44: IGN-04 | D44: =IF($C44="","",IFERROR(VLOOKUP($C44,Map_Register!$A$2:$C$5,3,FALSE()),"")) -> Toponym Labels | E44: Border | F44: Line- Municipal Boundary | G44: Segment 1- Municipal Boundary | H44: Absent | I44: Yes | J44: Yes | K44: overlap with international boundary | L44: No | O44: https://centrodedescargas.cnig.es/CentroDescargas/detalleArchivo?sec=9000029
A45: =IF($B45="","",ROW()-1) -> 44 | B45: IGN | C45: IGN-04 | D45: =IF($C45="","",IFERROR(VLOOKUP($C45,Map_Register!$A$2:$C$5,3,FALSE()),"")) -> Toponym Labels | E45: Border | F45: Line- Autonomous Community Boundary | G45: Segment 2 - Autonomous Community and Natural Park and other | H45: Present | K45: Autonomous Community boundary rendered. Overlap with province boundaries and municipal but only Autonomous Community boundary is rendered.jointly with natural park boundary | O45: https://centrodedescargas.cnig.es/CentroDescargas/detalleArchivo?sec=9000029
A46: =IF($B46="","",ROW()-1) -> 45 | B46: IGN | C46: IGN-04 | D46: =IF($C46="","",IFERROR(VLOOKUP($C46,Map_Register!$A$2:$C$5,3,FALSE()),"")) -> Toponym Labels | E46: Border | F46: Line- Municipal Boundary | G46: Segment 3 -Municipal Boundary | H46: Present | K46: municipal boundary | O46: https://centrodedescargas.cnig.es/CentroDescargas/detalleArchivo?sec=9000029
A47: =IF($B47="","",ROW()-1) -> 46 | B47: IGN | C47: IGN-04 | D47: =IF($C47="","",IFERROR(VLOOKUP($C47,Map_Register!$A$2:$C$5,3,FALSE()),"")) -> Toponym Labels | E47: Border | F47: Line- Municipal Boundary | G47: Segment 4 - Municipal Boundary | H47: Present | K47: municipal boundary | O47: https://centrodedescargas.cnig.es/CentroDescargas/detalleArchivo?sec=9000029
A48: =IF($B48="","",ROW()-1) -> 47 | B48: IGN | C48: IGN-04 | D48: =IF($C48="","",IFERROR(VLOOKUP($C48,Map_Register!$A$2:$C$5,3,FALSE()),"")) -> Toponym Labels | E48: Border | F48: Line- Municipal Boundary | G48: Segment 5 - Municipal Boundary | H48: Present | K48: municipal boundary | O48: https://centrodedescargas.cnig.es/CentroDescargas/detalleArchivo?sec=9000029
A49: =IF($B49="","",ROW()-1) -> 48 | B49: IGN | C49: IGN-04 | D49: =IF($C49="","",IFERROR(VLOOKUP($C49,Map_Register!$A$2:$C$5,3,FALSE()),"")) -> Toponym Labels | E49: Border | F49: Line- Municipal Boundary | G49: Segment 6 - Municipal Boundary | H49: Present | K49: municipal boundary | O49: https://centrodedescargas.cnig.es/CentroDescargas/detalleArchivo?sec=9000029
A50: =IF($B50="","",ROW()-1) -> 49 | B50: IGN | C50: IGN-04 | D50: =IF($C50="","",IFERROR(VLOOKUP($C50,Map_Register!$A$2:$C$5,3,FALSE()),"")) -> Toponym Labels | E50: Border | F50: Line- Municipal Boundary | G50: Segment 7 - Municipal Boundary | H50: Present | K50: municipal boundary | O50: https://centrodedescargas.cnig.es/CentroDescargas/detalleArchivo?sec=9000029
A51: =IF($B51="","",ROW()-1) -> 50 | B51: IGN | C51: IGN-04 | D51: =IF($C51="","",IFERROR(VLOOKUP($C51,Map_Register!$A$2:$C$5,3,FALSE()),"")) -> Toponym Labels | E51: Border | F51: Line- Municipal Boundary | G51: Segment 8 - Municipal Boundary | H51: Present | K51: municipal boundary | O51: https://centrodedescargas.cnig.es/CentroDescargas/detalleArchivo?sec=9000029
A52: =IF($B52="","",ROW()-1) -> 51 | B52: IGN | C52: IGN-04 | D52: =IF($C52="","",IFERROR(VLOOKUP($C52,Map_Register!$A$2:$C$5,3,FALSE()),"")) -> Toponym Labels | E52: Border | F52: Line- Municipal Boundary | G52: Segment 9 - Municipal Boundary | H52: Present | K52: municipal boundary | O52: https://centrodedescargas.cnig.es/CentroDescargas/detalleArchivo?sec=9000029
A53: =IF($B53="","",ROW()-1) -> 52 | B53: IGN | C53: IGN-04 | D53: =IF($C53="","",IFERROR(VLOOKUP($C53,Map_Register!$A$2:$C$5,3,FALSE()),"")) -> Toponym Labels | E53: Border | F53: Line- Municipal Boundary | G53: Segment 10 - Municipal Boundary | H53: Present | K53: municipal boundary | O53: https://centrodedescargas.cnig.es/CentroDescargas/detalleArchivo?sec=9000029
A54: =IF($B54="","",ROW()-1) -> 53 | B54: IGN | C54: IGN-04 | D54: =IF($C54="","",IFERROR(VLOOKUP($C54,Map_Register!$A$2:$C$5,3,FALSE()),"")) -> Toponym Labels | E54: Border | F54: Line- Municipal Boundary | G54: Segment 11 - Municipal Boundary | H54: Present | K54: municipal boundary | O54: https://centrodedescargas.cnig.es/CentroDescargas/detalleArchivo?sec=9000029
A55: =IF($B55="","",ROW()-1) -> 54 | B55: IGN | C55: IGN-04 | D55: =IF($C55="","",IFERROR(VLOOKUP($C55,Map_Register!$A$2:$C$5,3,FALSE()),"")) -> Toponym Labels | E55: Border | F55: Line- Municipal Boundary | G55: Segment 12 - Municipal Boundary | H55: Present | K55: municipal boundary | O55: https://centrodedescargas.cnig.es/CentroDescargas/detalleArchivo?sec=9000029
A56: =IF($B56="","",ROW()-1) -> 55 | B56: IGN | C56: IGN-04 | D56: =IF($C56="","",IFERROR(VLOOKUP($C56,Map_Register!$A$2:$C$5,3,FALSE()),"")) -> Toponym Labels | E56: Border | F56: Line- Municipal Boundary | G56: Segment 13 -Municipal Boundary | H56: Present | K56: municipal boundary | O56: https://centrodedescargas.cnig.es/CentroDescargas/detalleArchivo?sec=9000029
... A61: =IF($B61="","",ROW()-1) -> 60 | B61: IGN | C61: IGN-04 | D61: =IF($C61="","",IFERROR(VLOOKUP($C61,Map_Register!$A$2:$C$5,3,FALSE()),"")) -> Toponym Labels | E61: Border | F61: Line- Natural Park and other | G61: Segment 19- Natural Park and other | H61: Present | K61: rendered as natural park boundary; overlaps a portion of segment 1 where international boundary is rendered. | O61: map itself ; OSM
A222: =IF($B222="","",ROW()-1) | D222: =IF($C222="","",IFERROR(VLOOKUP($C222,Map_Register!$A$2:$C$5,3,FALSE()),""))
A223: =IF($B223="","",ROW()-1) | D223: =IF($C223="","",IFERROR(VLOOKUP($C223,Map_Register!$A$2:$C$5,3,FALSE()),""))
A224: =IF($B224="","",ROW()-1) | D224: =IF($C224="","",IFERROR(VLOOKUP($C224,Map_Register!$A$2:$C$5,3,FALSE()),""))
A225: =IF($B225="","",ROW()-1) | D225: =IF($C225="","",IFERROR(VLOOKUP($C225,Map_Register!$A$2:$C$5,3,FALSE()),""))
A226: =IF($B226="","",ROW()-1) | D226: =IF($C226="","",IFERROR(VLOOKUP($C226,Map_Register!$A$2:$C$5,3,FALSE()),""))
A227: =IF($B227="","",ROW()-1) | D227: =IF($C227="","",IFERROR(VLOOKUP($C227,Map_Register!$A$2:$C$5,3,FALSE()),""))
A228: =IF($B228="","",ROW()-1) | D228: =IF($C228="","",IFERROR(VLOOKUP($C228,Map_Register!$A$2:$C$5,3,FALSE()),""))
A229: =IF($B229="","",ROW()-1) | D229: =IF($C229="","",IFERROR(VLOOKUP($C229,Map_Register!$A$2:$C$5,3,FALSE()),""))
A230: =IF($B230="","",ROW()-1) | D230: =IF($C230="","",IFERROR(VLOOKUP($C230,Map_Register!$A$2:$C$5,3,FALSE()),""))
A231: =IF($B231="","",ROW()-1) | D231: =IF($C231="","",IFERROR(VLOOKUP($C231,Map_Register!$A$2:$C$5,3,FALSE()),""))
A232: =IF($B232="","",ROW()-1) | D232: =IF($C232="","",IFERROR(VLOOKUP($C232,Map_Register!$A$2:$C$5,3,FALSE()),""))
A233: =IF($B233="","",ROW()-1) | D233: =IF($C233="","",IFERROR(VLOOKUP($C233,Map_Register!$A$2:$C$5,3,FALSE()),""))
... A518: =IF($B518="","",ROW()-1) | D518: =IF($C518="","",IFERROR(VLOOKUP($C518,Map_Register!$A$2:$C$5,3,FALSE()),""))

Sheet Spain_Military
A1: Record_ID | B1: NMA | C1: Map_ID | D1: Sheet_Type | E1: Category | F1: Feature_Type | G1: Name(If Available) | H1: Code | I1: RenderingStage_Flag | J1: Generalization_Flag | K1: Justification | L1: Specification_Flag | M1: Feature_Count | N1: Bertin_Variable | O1: Reference_Source
A2: =IF($B2="","",ROW()-1) -> 1 | B2: IGN | C2: IGN-03 | D2: =IF($C2="","",IFERROR(VLOOKUP($C2,Map_Register!$A$2:$C$5,3,FALSE()),"")) -> Military Zone | E2: Military | F2: Restricted area polygon | G2: Base Naval Aerodromo de Cadis / Rota | H2: Absent | I2: NA | J2: No | K2: No indication of restricted area or military use | L2: Yes | O2: https://armada.defensa.gob.es/ArmadaPortal/page/Portal/ArmadaEspannola/conocenosorganizacion/prefLang-es/04Apoyofuerza--02jal--05Arsenales--01arsenalcadiz ; OSM
A3: =IF($B3="","",ROW()-1) -> 2 | B3: IGN | C3: IGN-03 | D3: =IF($C3="","",IFERROR(VLOOKUP($C3,Map_Register!$A$2:$C$5,3,FALSE()),"")) -> Military Zone | E3: Military | F3: Label | G3: Puerto de la Base Aeronaval de la Rota | H3: Present | K3: Label of Aero-Naval base in Rota; Under local authoritaties label | O3: Map itself
A4: =IF($B4="","",ROW()-1) -> 3 | B4: IGN | C4: IGN-03 | D4: =IF($C4="","",IFERROR(VLOOKUP($C4,Map_Register!$A$2:$C$5,3,FALSE()),"")) -> Military Zone | E4: Military | F4: Label | G4: Base Naval Aerodromo de Cadiz / Rota | H4: Present | K4: Label of Naval Base in Cadiz / Rota; Under local authorities label | O4: Map itself
A5: =IF($B5="","",ROW()-1) -> 4 | B5: IGN | C5: IGN-01 | D5: =IF($C5="","",IFERROR(VLOOKUP($C5,Map_Register!$A$2:$C$5,3,FALSE()),"")) -> Border Region | E5: Military | F5: Label | G5: Base Naval de Gibraltar | H5: Present | K5: Label of Naval Base in Gibraltar | O5: Map itself
A6: =IF($B6="","",ROW()-1) -> 5 | B6: IGN | C6: IGN-01 | D6: =IF($C6="","",IFERROR(VLOOKUP($C6,Map_Register!$A$2:$C$5,3,FALSE()),"")) -> Border Region | E6: Military | F6: Label | G6: Acuartelameineto Adalides | H6: Present | K6: Label of Barracks | O6: https://www.boe.es/diario_boe/txt.php?id=BOE-A-1998-17931
A7: =IF($B7="","",ROW()-1) -> 6 | B7: IGN | C7: IGN-01 | D7: =IF($C7="","",IFERROR(VLOOKUP($C7,Map_Register!$A$2:$C$5,3,FALSE()),"")) -> Border Region | E7: Military | F7: Restricted area polygon | G7: HM Naval Base Gibraltar | H7: Absent | I7: NA | J7: No | K7: No indication of restricted area or military use | L7: Yes | O7: https://www.gov.uk/ ; OSM
A8: =IF($B8="","",ROW()-1) -> 7 | B8: IGN | C8: IGN-02 | D8: =IF($C8="","",IFERROR(VLOOKUP($C8,Map_Register!$A$2:$C$5,3,FALSE()),"")) -> Cultural Heritage Area | E8: Military | F8: Military Headquarters | G8: Cuartel General de la Fuerza Terrestre | H8: Present | K8: Singular building with label "Antigua Capitania General " | O8: https://ejercito.defensa.gob.es/unidades/Sevilla/futer/ ; OSM
A9: =IF($B9="","",ROW()-1) -> 8 | B9: IGN | C9: IGN-02 | D9: =IF($C9="","",IFERROR(VLOOKUP($C9,Map_Register!$A$2:$C$5,3,FALSE()),"")) -> Cultural Heritage Area | E9: Military | F9: Military Barracks | G9: Acuartelamiento La Borbolla | H9: Absent | I9: NA | J9: No | K9: No indication of restricted area or military use | L9: Yes | O9: https://ejercito.defensa.gob.es/unidades/Sevilla/suigesur/Localizacion/index.html ; OSM
D10: =IF($C10="","",IFERROR(VLOOKUP($C10,Map_Register!$A$2:$C$5,3,FALSE()),""))
D11: =IF($C11="","",IFERROR(VLOOKUP($C11,Map_Register!$A$2:$C$5,3,FALSE()),""))
D12: =IF($C12="","",IFERROR(VLOOKUP($C12,Map_Register!$A$2:$C$5,3,FALSE()),""))
D13: =IF($C13="","",IFERROR(VLOOKUP($C13,Map_Register!$A$2:$C$5,3,FALSE()),""))
D14: =IF($C14="","",IFERROR(VLOOKUP($C14,Map_Register!$A$2:$C$5,3,FALSE()),""))
D15: =IF($C15="","",IFERROR(VLOOKUP($C15,Map_Register!$A$2:$C$5,3,FALSE()),""))
D16: =IF($C16="","",IFERROR(VLOOKUP($C16,Map_Register!$A$2:$C$5,3,FALSE()),""))
D17: =IF($C17="","",IFERROR(VLOOKUP($C17,Map_Register!$A$2:$C$5,3,FALSE()),""))
D18: =IF($C18="","",IFERROR(VLOOKUP($C18,Map_Register!$A$2:$C$5,3,FALSE()),""))
D19: =IF($C19="","",IFERROR(VLOOKUP($C19,Map_Register!$A$2:$C$5,3,FALSE()),""))
D20: =IF($C20="","",IFERROR(VLOOKUP($C20,Map_Register!$A$2:$C$5,3,FALSE()),""))
D21: =IF($C21="","",IFERROR(VLOOKUP($C21,Map_Register!$A$2:$C$5,3,FALSE()),""))
... D26: =IF($C26="","",IFERROR(VLOOKUP($C26,Map_Register!$A$2:$C$5,3,FALSE()),""))
A208: =IF($B208="","",ROW()-1) | D208: =IF($C208="","",IFERROR(VLOOKUP($C208,Map_Register!$A$2:$C$5,3,FALSE()),""))
A209: =IF($B209="","",ROW()-1) | D209: =IF($C209="","",IFERROR(VLOOKUP($C209,Map_Register!$A$2:$C$5,3,FALSE()),""))
A210: =IF($B210="","",ROW()-1) | D210: =IF($C210="","",IFERROR(VLOOKUP($C210,Map_Register!$A$2:$C$5,3,FALSE()),""))
A211: =IF($B211="","",ROW()-1) | D211: =IF($C211="","",IFERROR(VLOOKUP($C211,Map_Register!$A$2:$C$5,3,FALSE()),""))
A212: =IF($B212="","",ROW()-1) | D212: =IF($C212="","",IFERROR(VLOOKUP($C212,Map_Register!$A$2:$C$5,3,FALSE()),""))
A213: =IF($B213="","",ROW()-1) | D213: =IF($C213="","",IFERROR(VLOOKUP($C213,Map_Register!$A$2:$C$5,3,FALSE()),""))
A214: =IF($B214="","",ROW()-1) | D214: =IF($C214="","",IFERROR(VLOOKUP($C214,Map_Register!$A$2:$C$5,3,FALSE()),""))
A215: =IF($B215="","",ROW()-1) | D215: =IF($C215="","",IFERROR(VLOOKUP($C215,Map_Register!$A$2:$C$5,3,FALSE()),""))
A216: =IF($B216="","",ROW()-1) | D216: =IF($C216="","",IFERROR(VLOOKUP($C216,Map_Register!$A$2:$C$5,3,FALSE()),""))
A217: =IF($B217="","",ROW()-1) | D217: =IF($C217="","",IFERROR(VLOOKUP($C217,Map_Register!$A$2:$C$5,3,FALSE()),""))
A218: =IF($B218="","",ROW()-1) | D218: =IF($C218="","",IFERROR(VLOOKUP($C218,Map_Register!$A$2:$C$5,3,FALSE()),""))
A219: =IF($B219="","",ROW()-1) | D219: =IF($C219="","",IFERROR(VLOOKUP($C219,Map_Register!$A$2:$C$5,3,FALSE()),""))
... A504: =IF($B504="","",ROW()-1) | D504: =IF($C504="","",IFERROR(VLOOKUP($C504,Map_Register!$A$2:$C$5,3,FALSE()),""))

Sheet Spain_Toponym
A1: Record_ID | B1: NMA | C1: Map_ID | D1: Sheet_Type | E1: Category | F1: FID | G1: Feature_Type | H1: Name(If Available) | I1: Languages | J1: Code | K1: RenderingStage_Flag | L1: Generalization_Flag | M1: Justification | N1: Specification_Flag | O1: Feature_Count | P1: Bertin_Variable | Q1: Reference_Source
A2: =IF($B2="","",ROW()-1) -> 1 | B2: IGN | C2: IGN-04 | D2: =IF($C2="","",IFERROR(VLOOKUP($C2,Map_Register!$A$2:$C$5,3,FALSE()),"")) -> Toponym Labels | E2: Toponym | F2: 46 | G2: Park | H2: Parque Natural Señorío de Bertiz | I2: Spanish | J2: Present (Emphasized) | M2: all caps; size of letter | Q2: https://centrodedescargas.cnig.es/CentroDescargas/btn-poi
A3: =IF($B3="","",ROW()-1) -> 2 | B3: IGN | C3: IGN-04 | D3: =IF($C3="","",IFERROR(VLOOKUP($C3,Map_Register!$A$2:$C$5,3,FALSE()),"")) -> Toponym Labels | E3: Toponym | F3: 177 | G3: Natural Reserve | H3: Reserva Natural San Juan Xar | I3: Spanish | J3: Absent | K3: Yes | L3: Yes | M3: No label found; limited space for label and other labels nearby | N3: No | Q3: https://centrodedescargas.cnig.es/CentroDescargas/btn-poi
A4: =IF($B4="","",ROW()-1) -> 3 | B4: IGN | C4: IGN-04 | D4: =IF($C4="","",IFERROR(VLOOKUP($C4,Map_Register!$A$2:$C$5,3,FALSE()),"")) -> Toponym Labels | E4: Toponym | F4: 216 | G4: Natural Reserve | H4: Reserva Natural Labiaga | I4: Spanish | J4: Present | M4: only Labeaga | Q4: https://centrodedescargas.cnig.es/CentroDescargas/btn-poi
A5: =IF($B5="","",ROW()-1) -> 4 | B5: IGN | C5: IGN-04 | D5: =IF($C5="","",IFERROR(VLOOKUP($C5,Map_Register!$A$2:$C$5,3,FALSE()),"")) -> Toponym Labels | E5: Toponym | F5: 323 | G5: Natural Monument | H5: Monumento Natural Tejo de Etxalar | I5: Spanish | J5: Present | M5: another similar label | Q5: https://centrodedescargas.cnig.es/CentroDescargas/btn-poi
A6: =IF($B6="","",ROW()-1) -> 5 | B6: IGN | C6: IGN-04 | D6: =IF($C6="","",IFERROR(VLOOKUP($C6,Map_Register!$A$2:$C$5,3,FALSE()),"")) -> Toponym Labels | E6: Toponym | F6: 378 | G6: Natural Monument | H6: Monumento Natural Acebo de Bera | I6: Spanish | J6: Present | M6: Acebo de Bera | Q6: https://centrodedescargas.cnig.es/CentroDescargas/btn-poi
A7: =IF($B7="","",ROW()-1) -> 6 | B7: IGN | C7: IGN-04 | D7: =IF($C7="","",IFERROR(VLOOKUP($C7,Map_Register!$A$2:$C$5,3,FALSE()),"")) -> Toponym Labels | E7: Toponym | F7: 396 | G7: Natural Monument | H7: Monumento Natural Peral de Bera | I7: Spanish | J7: Present | M7: Peral de Bera/ Berako Udareondoa ; separated by slash | Q7: https://centrodedescargas.cnig.es/CentroDescargas/btn-poi
A8: =IF($B8="","",ROW()-1) -> 7 | B8: IGN | C8: IGN-04 | D8: =IF($C8="","",IFERROR(VLOOKUP($C8,Map_Register!$A$2:$C$5,3,FALSE()),"")) -> Toponym Labels | E8: Toponym | F8: 436 | G8: Natural Monument | H8: Monumento Natural Sequoya del Embalse de Domiko | I8: Spanish | J8: Present | M8: similar label | Q8: https://centrodedescargas.cnig.es/CentroDescargas/btn-poi
A9: =IF($B9="","",ROW()-1) -> 8 | B9: IGN | C9: IGN-04 | D9: =IF($C9="","",IFERROR(VLOOKUP($C9,Map_Register!$A$2:$C$5,3,FALSE()),"")) -> Toponym Labels | E9: Toponym | F9: 1020 | G9: Tree | H9: Acebo de Bera/Berako gorostia | I9: Basque | J9: Present | M9: Both labels present ; slash seprated ; equal visual weight; individual tree | Q9: https://centrodedescargas.cnig.es/CentroDescargas/btn-poi
A10: =IF($B10="","",ROW()-1) -> 9 | B10: IGN | C10: IGN-04 | D10: =IF($C10="","",IFERROR(VLOOKUP($C10,Map_Register!$A$2:$C$5,3,FALSE()),"")) -> Toponym Labels | E10: Toponym | F10: 1022 | G10: Tree | H10: Peral de Bera/Berako udareondoa | I10: Basque | J10: Present | M10: as Peral de Bera ; sett name? | Q10: https://centrodedescargas.cnig.es/CentroDescargas/btn-poi
A11: =IF($B11="","",ROW()-1) -> 10 | B11: IGN | C11: IGN-04 | D11: =IF($C11="","",IFERROR(VLOOKUP($C11,Map_Register!$A$2:$C$5,3,FALSE()),"")) -> Toponym Labels | E11: Toponym | F11: 1036 | G11: Tree | H11: Sequoya del Embalse de Domiko/Domikoko Urtegiko sekuoia | I11: Basque | J11: Present | M11: both names appear separated by / | Q11: https://centrodedescargas.cnig.es/CentroDescargas/btn-poi
A12: =IF($B12="","",ROW()-1) -> 11 | B12: IGN | C12: IGN-04 | D12: =IF($C12="","",IFERROR(VLOOKUP($C12,Map_Register!$A$2:$C$5,3,FALSE()),"")) -> Toponym Labels | E12: Toponym | F12: 1037 | G12: Tree | H12: Tejo de Etxalar/Etxalarko hagina | I12: Basque | J12: Present | M12: label styled as Tree | Q12: https://centrodedescargas.cnig.es/CentroDescargas/btn-poi
A13: =IF($B13="","",ROW()-1) -> 12 | B13: IGN | C13: IGN-04 | D13: =IF($C13="","",IFERROR(VLOOKUP($C13,Map_Register!$A$2:$C$5,3,FALSE()),"")) -> Toponym Labels | E13: Toponym | F13: 3152 | G13: Natural Cave | H13: Cuevas de Zugarramurdi | I13: Spanish | J13: Absent | K13: Yes | L13: Yes | M13: No label found; limited space for label and other labels nearby | N13: No | Q13: https://centrodedescargas.cnig.es/CentroDescargas/btn-poi
A14: =IF($B14="","",ROW()-1) -> 13 | B14: IGN | C14: IGN-04 | D14: =IF($C14="","",IFERROR(VLOOKUP($C14,Map_Register!$A$2:$C$5,3,FALSE()),"")) -> Toponym Labels | E14: Toponym | F14: 3771 | G14: Natural Cave | H14: Gruta de San Juan Xarr | I14: Spanish | J14: Absent | K14: Yes | L14: Yes | M14: No label found; limited space for label and other labels nearby | N14: No | Q14: https://centrodedescargas.cnig.es/CentroDescargas/btn-poi
A15: =IF($B15="","",ROW()-1) -> 14 | B15: IGN | C15: IGN-04 | D15: =IF($C15="","",IFERROR(VLOOKUP($C15,Map_Register!$A$2:$C$5,3,FALSE()),"")) -> Toponym Labels | E15: Toponym | F15: 4126 | G15: Natural Cave | H15: Gruta de la Bruja | I15: Spanish | J15: Absent | K15: Yes | L15: Yes | M15: No label found; limited space for label and other labels nearby | N15: No | Q15: https://centrodedescargas.cnig.es/CentroDescargas/btn-poi
A16: =IF($B16="","",ROW()-1) -> 15 | B16: IGN | C16: IGN-04 | D16: =IF($C16="","",IFERROR(VLOOKUP($C16,Map_Register!$A$2:$C$5,3,FALSE()),"")) -> Toponym Labels | E16: Toponym | F16: 5088 | G16: Short-Distance Trail | H16: PR-GI-1007 (Antigua Via Férrea de Artikutza) | I16: Spanish | J16: Absent | K16: Yes | L16: Yes | M16: No label found; limited space for label and other labels nearby | N16: No | Q16: https://centrodedescargas.cnig.es/CentroDescargas/btn-poi
A17: =IF($B17="","",ROW()-1) -> 16 | B17: IGN | C17: IGN-04 | D17: =IF($C17="","",IFERROR(VLOOKUP($C17,Map_Register!$A$2:$C$5,3,FALSE()),"")) -> Toponym Labels | E17: Toponym | F17: 8156 | G17: Other routes | H17: SL-GI 1006 (Cascada de Aitzondo) | I17: Spanish | J17: Absent | K17: Yes | L17: Yes | M17: No label found; limited space for label and other labels nearby | N17: No | Q17: https://centrodedescargas.cnig.es/CentroDescargas/btn-poi
A18: =IF($B18="","",ROW()-1) -> 17 | B18: IGN | C18: IGN-04 | D18: =IF($C18="","",IFERROR(VLOOKUP($C18,Map_Register!$A$2:$C$5,3,FALSE()),"")) -> Toponym Labels | E18: Toponym | F18: 8388 | G18: Long-Distance Trail | H18: GR 11 (Etapa 02. Bera-Elizondo) | I18: Spanish | J18: Absent | K18: Yes | L18: Yes | M18: road? | N18: No | Q18: https://centrodedescargas.cnig.es/CentroDescargas/btn-poi
A19: =IF($B19="","",ROW()-1) -> 18 | B19: IGN | C19: IGN-04 | D19: =IF($C19="","",IFERROR(VLOOKUP($C19,Map_Register!$A$2:$C$5,3,FALSE()),"")) -> Toponym Labels | E19: Toponym | F19: 16969 | G19: Region | H19: Montes de Bidasoa | I19: Spanish | J19: Present | M19: Label styled as region | Q19: https://centrodedescargas.cnig.es/CentroDescargas/btn-poi
A20: =IF($B20="","",ROW()-1) -> 19 | B20: IGN | C20: IGN-04 | D20: =IF($C20="","",IFERROR(VLOOKUP($C20,Map_Register!$A$2:$C$5,3,FALSE()),"")) -> Toponym Labels | E20: Toponym | F20: 102008 | G20: Landscape | H20: Orozko-Zubieta | I20: Basque | J20: Present | M20: labelled as landscape | Q20: https://centrodedescargas.cnig.es/CentroDescargas/btn-poi
A21: =IF($B21="","",ROW()-1) -> 20 | B21: IGN | C21: IGN-04 | D21: =IF($C21="","",IFERROR(VLOOKUP($C21,Map_Register!$A$2:$C$5,3,FALSE()),"")) -> Toponym Labels | E21: Toponym | F21: 102009 | G21: Landscape | H21: Guruspil | I21: Basque | J21: Absent | K21: Yes | L21: No | M21: Label not found; enough space for label; generalization is unlikely- space for label is available | N21: No | Q21: https://centrodedescargas.cnig.es/CentroDescargas/btn-poi
A22: =IF($B22="","",ROW()-1) -> 21 | B22: IGN | C22: IGN-04 | D22: =IF($C22="","",IFERROR(VLOOKUP($C22,Map_Register!$A$2:$C$5,3,FALSE()),"")) -> Toponym Labels | E22: Toponym | F22: 102010 | G22: Landscape | H22: Cantera de Idiburuta | I22: Basque | J22: Present | M22: labelled as landscape | Q22: https://centrodedescargas.cnig.es/CentroDescargas/btn-poi
A23: =IF($B23="","",ROW()-1) -> 22 | B23: IGN | C23: IGN-04 | D23: =IF($C23="","",IFERROR(VLOOKUP($C23,Map_Register!$A$2:$C$5,3,FALSE()),"")) -> Toponym Labels | E23: Toponym | F23: 102011 | G23: Landscape | H23: Gogorregia | I23: Basque | J23: Absent | K23: Yes | L23: No | M23: Label not found; enough space for label; generalization is unlikely- space for label is available | N23: No | Q23: https://centrodedescargas.cnig.es/CentroDescargas/btn-poi
A24: =IF($B24="","",ROW()-1) -> 23 | B24: IGN | C24: IGN-04 | D24: =IF($C24="","",IFERROR(VLOOKUP($C24,Map_Register!$A$2:$C$5,3,FALSE()),"")) -> Toponym Labels | E24: Toponym | F24: 102012 | G24: Landscape | H24: Loma de Alegi | I24: Basque | J24: Present | M24: labelled as landscape | Q24: https://centrodedescargas.cnig.es/CentroDescargas/btn-poi
A25: =IF($B25="","",ROW()-1) -> 24 | B25: IGN | C25: IGN-04 | D25: =IF($C25="","",IFERROR(VLOOKUP($C25,Map_Register!$A$2:$C$5,3,FALSE()),"")) -> Toponym Labels | E25: Toponym | F25: 102013 | G25: Landscape | H25: Loma de Elutxea | I25: Basque | J25: Present | M25: labelled as landscape | Q25: https://centrodedescargas.cnig.es/CentroDescargas/btn-poi
A26: =IF($B26="","",ROW()-1) -> 25 | B26: IGN | C26: IGN-04 | D26: =IF($C26="","",IFERROR(VLOOKUP($C26,Map_Register!$A$2:$C$5,3,FALSE()),"")) -> Toponym Labels | E26: Toponym | F26: 102014 | G26: Landscape | H26: Amekurrun | I26: Basque | J26: Present | M26: labelled as landscape | Q26: https://centrodedescargas.cnig.es/CentroDescargas/btn-poi
A27: =IF($B27="","",ROW()-1) -> 26 | B27: IGN | C27: IGN-04 | D27: =IF($C27="","",IFERROR(VLOOKUP($C27,Map_Register!$A$2:$C$5,3,FALSE()),"")) -> Toponym Labels | E27: Toponym | F27: 102015 | G27: Landscape | H27: Jaral de Pagola | I27: Basque | J27: Absent | K27: Yes | L27: No | M27: Label not found; enough space for label; generalization is unlikely- space for label is available | N27: No | Q27: https://centrodedescargas.cnig.es/CentroDescargas/btn-poi
A28: =IF($B28="","",ROW()-1) -> 27 | B28: IGN | C28: IGN-04 | D28: =IF($C28="","",IFERROR(VLOOKUP($C28,Map_Register!$A$2:$C$5,3,FALSE()),"")) -> Toponym Labels | E28: Toponym | F28: 102063 | G28: Landscape | H28: Olistieta | I28: Basque | J28: Absent | K28: Yes | L28: No | M28: Label not found; enough space for label; generalization is unlikely- space for label is available | N28: No | Q28: https://centrodedescargas.cnig.es/CentroDescargas/btn-poi
A29: =IF($B29="","",ROW()-1) -> 28 | B29: IGN | C29: IGN-04 | D29: =IF($C29="","",IFERROR(VLOOKUP($C29,Map_Register!$A$2:$C$5,3,FALSE()),"")) -> Toponym Labels | E29: Toponym | F29: 102064 | G29: Landscape | H29: Benaitxoro | I29: Basque | J29: Present | M29: labelled as landscape | Q29: https://centrodedescargas.cnig.es/CentroDescargas/btn-poi
A30: =IF($B30="","",ROW()-1) -> 29 | B30: IGN | C30: IGN-04 | D30: =IF($C30="","",IFERROR(VLOOKUP($C30,Map_Register!$A$2:$C$5,3,FALSE()),"")) -> Toponym Labels | E30: Toponym | F30: 102065 | G30: Landscape | H30: Otan | I30: Basque | J30: Present | M30: labelled as landscape | Q30: https://centrodedescargas.cnig.es/CentroDescargas/btn-poi
A31: =IF($B31="","",ROW()-1) -> 30 | B31: IGN | C31: IGN-04 | D31: =IF($C31="","",IFERROR(VLOOKUP($C31,Map_Register!$A$2:$C$5,3,FALSE()),"")) -> Toponym Labels | E31: Toponym | F31: 102066 | G31: Landscape | H31: Ametxoko | I31: Basque | J31: Present | M31: one present as Ametxoko Borda | Q31: https://centrodedescargas.cnig.es/CentroDescargas/btn-poi
A32: =IF($B32="","",ROW()-1) -> 31 | B32: IGN | C32: IGN-04 | D32: =IF($C32="","",IFERROR(VLOOKUP($C32,Map_Register!$A$2:$C$5,3,FALSE()),"")) -> Toponym Labels | E32: Toponym | F32: 102067 | G32: Landscape | H32: Iturla | I32: Basque | J32: Absent | K32: Yes | L32: No | M32: Label not found; enough space for label; generalization is unlikely- space for label is available | N32: No | Q32: https://centrodedescargas.cnig.es/CentroDescargas/btn-poi
A33: =IF($B33="","",ROW()-1) -> 32 | B33: IGN | C33: IGN-04 | D33: =IF($C33="","",IFERROR(VLOOKUP($C33,Map_Register!$A$2:$C$5,3,FALSE()),"")) -> Toponym Labels | E33: Toponym | F33: 102068 | G33: Landscape | H33: Ibintza | I33: Basque | J33: Present | M33: labelled as landscape | Q33: https://centrodedescargas.cnig.es/CentroDescargas/btn-poi
A34: =IF($B34="","",ROW()-1) -> 33 | B34: IGN | C34: IGN-04 | D34: =IF($C34="","",IFERROR(VLOOKUP($C34,Map_Register!$A$2:$C$5,3,FALSE()),"")) -> Toponym Labels | E34: Toponym | F34: 102072 | G34: Landscape | H34: Mugaosekogaña | I34: Basque | J34: Absent | K34: Yes | L34: Yes | M34: No label found; limited space for label and other labels nearby | N34: No | Q34: https://centrodedescargas.cnig.es/CentroDescargas/btn-poi
A35: =IF($B35="","",ROW()-1) -> 34 | B35: IGN | C35: IGN-04 | D35: =IF($C35="","",IFERROR(VLOOKUP($C35,Map_Register!$A$2:$C$5,3,FALSE()),"")) -> Toponym Labels | E35: Toponym | F35: 102415 | G35: Landscape | H35: Txingorri-Azpie | I35: Basque | J35: Present | M35: labelled as landscape | Q35: https://centrodedescargas.cnig.es/CentroDescargas/btn-poi
A36: =IF($B36="","",ROW()-1) -> 35 | B36: IGN | C36: IGN-04 | D36: =IF($C36="","",IFERROR(VLOOKUP($C36,Map_Register!$A$2:$C$5,3,FALSE()),"")) -> Toponym Labels | E36: Toponym | F36: 102416 | G36: Landscape | H36: Lardi-Lepo | I36: Basque | J36: Present | M36: labelled as landscape | Q36: https://centrodedescargas.cnig.es/CentroDescargas/btn-poi
A37: =IF($B37="","",ROW()-1) -> 36 | B37: IGN | C37: IGN-04 | D37: =IF($C37="","",IFERROR(VLOOKUP($C37,Map_Register!$A$2:$C$5,3,FALSE()),"")) -> Toponym Labels | E37: Toponym | F37: 102417 | G37: Landscape | H37: Zarkinza | I37: Basque | J37: Absent | K37: Yes | L37: No | M37: Label not found; enough space for label; generalization is unlikely- space for label is available | N37: No | Q37: https://centrodedescargas.cnig.es/CentroDescargas/btn-poi
A38: =IF($B38="","",ROW()-1) -> 37 | B38: IGN | C38: IGN-04 | D38: =IF($C38="","",IFERROR(VLOOKUP($C38,Map_Register!$A$2:$C$5,3,FALSE()),"")) -> Toponym Labels | E38: Toponym | F38: 102418 | G38: Landscape | H38: Ikatzola | I38: Basque | J38: Present | M38: labelled as landscape | Q38: https://centrodedescargas.cnig.es/CentroDescargas/btn-poi
A39: =IF($B39="","",ROW()-1) -> 38 | B39: IGN | C39: IGN-04 | D39: =IF($C39="","",IFERROR(VLOOKUP($C39,Map_Register!$A$2:$C$5,3,FALSE()),"")) -> Toponym Labels | E39: Toponym | F39: 102419 | G39: Landscape | H39: Usorbide | I39: Basque | J39: Absent | K39: Yes | L39: No | M39: No name found | N39: No | Q39: https://centrodedescargas.cnig.es/CentroDescargas/btn-poi
A40: =IF($B40="","",ROW()-1) -> 39 | B40: IGN | C40: IGN-04 | D40: =IF($C40="","",IFERROR(VLOOKUP($C40,Map_Register!$A$2:$C$5,3,FALSE()),"")) -> Toponym Labels | E40: Toponym | F40: 102420 | G40: Landscape | H40: Usku | I40: Basque | J40: Present | M40: labelled as landscape | Q40: https://centrodedescargas.cnig.es/CentroDescargas/btn-poi
A41: =IF($B41="","",ROW()-1) -> 40 | B41: IGN | C41: IGN-04 | D41: =IF($C41="","",IFERROR(VLOOKUP($C41,Map_Register!$A$2:$C$5,3,FALSE()),"")) -> Toponym Labels | E41: Toponym | F41: 102421 | G41: Landscape | H41: Istu | I41: Basque | J41: Present | M41: labelled as landscape | Q41: https://centrodedescargas.cnig.es/CentroDescargas/btn-poi
A42: =IF($B42="","",ROW()-1) -> 41 | B42: IGN | C42: IGN-04 | D42: =IF($C42="","",IFERROR(VLOOKUP($C42,Map_Register!$A$2:$C$5,3,FALSE()),"")) -> Toponym Labels | E42: Toponym | F42: 102422 | G42: Landscape | H42: Txorikantari | I42: Basque | J42: Present | M42: labelled as landscape | Q42: https://centrodedescargas.cnig.es/CentroDescargas/btn-poi
A43: =IF($B43="","",ROW()-1) -> 42 | B43: IGN | C43: IGN-04 | D43: =IF($C43="","",IFERROR(VLOOKUP($C43,Map_Register!$A$2:$C$5,3,FALSE()),"")) -> Toponym Labels | E43: Toponym | F43: 102423 | G43: Landscape | H43: Beltzuntze | I43: Basque | J43: Present | M43: labelled as landscape | Q43: https://centrodedescargas.cnig.es/CentroDescargas/btn-poi
A44: =IF($B44="","",ROW()-1) -> 43 | B44: IGN | C44: IGN-04 | D44: =IF($C44="","",IFERROR(VLOOKUP($C44,Map_Register!$A$2:$C$5,3,FALSE()),"")) -> Toponym Labels | E44: Toponym | F44: 102424 | G44: Landscape | H44: Agila | I44: Basque | J44: Present | M44: labelled as landscape | Q44: https://centrodedescargas.cnig.es/CentroDescargas/btn-poi
A45: =IF($B45="","",ROW()-1) -> 44 | B45: IGN | C45: IGN-04 | D45: =IF($C45="","",IFERROR(VLOOKUP($C45,Map_Register!$A$2:$C$5,3,FALSE()),"")) -> Toponym Labels | E45: Toponym | F45: 102425 | G45: Landscape | H45: Lasarteaga | I45: Basque | J45: Absent | K45: Yes | L45: Yes | M45: No label found; limited space for label and other labels nearby | N45: No | Q45: https://centrodedescargas.cnig.es/CentroDescargas/btn-poi
A46: =IF($B46="","",ROW()-1) -> 45 | B46: IGN | C46: IGN-04 | D46: =IF($C46="","",IFERROR(VLOOKUP($C46,Map_Register!$A$2:$C$5,3,FALSE()),"")) -> Toponym Labels | E46: Toponym | F46: 102426 | G46: Landscape | H46: Belaun | I46: Basque | J46: Present | M46: labelled as landscape | Q46: https://centrodedescargas.cnig.es/CentroDescargas/btn-poi
A47: =IF($B47="","",ROW()-1) -> 46 | B47: IGN | C47: IGN-04 | D47: =IF($C47="","",IFERROR(VLOOKUP($C47,Map_Register!$A$2:$C$5,3,FALSE()),"")) -> Toponym Labels | E47: Toponym | F47: 102427 | G47: Landscape | H47: Isastrin | I47: Basque | J47: Present | M47: labelled as landscape | Q47: https://centrodedescargas.cnig.es/CentroDescargas/btn-poi
A48: =IF($B48="","",ROW()-1) -> 47 | B48: IGN | C48: IGN-04 | D48: =IF($C48="","",IFERROR(VLOOKUP($C48,Map_Register!$A$2:$C$5,3,FALSE()),"")) -> Toponym Labels | E48: Toponym | F48: 102428 | G48: Landscape | H48: Larrondo | I48: Basque | J48: Absent | K48: Yes | L48: Yes | M48: No label found; limited space for label and other labels nearby | N48: No | Q48: https://centrodedescargas.cnig.es/CentroDescargas/btn-poi
A49: =IF($B49="","",ROW()-1) -> 48 | B49: IGN | C49: IGN-04 | D49: =IF($C49="","",IFERROR(VLOOKUP($C49,Map_Register!$A$2:$C$5,3,FALSE()),"")) -> Toponym Labels | E49: Toponym | F49: 102429 | G49: Landscape | H49: Elama | I49: Basque | J49: Absent | K49: Yes | L49: No | M49: Label not found; enough space for label; generalization is unlikely- space for label is available | N49: No | Q49: https://centrodedescargas.cnig.es/CentroDescargas/btn-poi
A50: =IF($B50="","",ROW()-1) -> 49 | B50: IGN | C50: IGN-04 | D50: =IF($C50="","",IFERROR(VLOOKUP($C50,Map_Register!$A$2:$C$5,3,FALSE()),"")) -> Toponym Labels | E50: Toponym | F50: 102430 | G50: Landscape | H50: Barrutiko-Erreka | I50: Basque | J50: Present | M50: labelled as landscape | Q50: https://centrodedescargas.cnig.es/CentroDescargas/btn-poi
A51: =IF($B51="","",ROW()-1) -> 50 | B51: IGN | C51: IGN-04 | D51: =IF($C51="","",IFERROR(VLOOKUP($C51,Map_Register!$A$2:$C$5,3,FALSE()),"")) -> Toponym Labels | E51: Toponym | F51: 102431 | G51: Landscape | H51: Aritzalun | I51: Basque | J51: Absent | K51: Yes | L51: No | M51: Label not found; enough space for label; generalization is unlikely- space for label is available | N51: No | Q51: https://centrodedescargas.cnig.es/CentroDescargas/btn-poi
A52: =IF($B52="","",ROW()-1) -> 51 | B52: IGN | C52: IGN-04 | D52: =IF($C52="","",IFERROR(VLOOKUP($C52,Map_Register!$A$2:$C$5,3,FALSE()),"")) -> Toponym Labels | E52: Toponym | F52: 102432 | G52: Landscape | H52: Franzesen | I52: Basque | J52: Absent | K52: Yes | L52: No | M52: Label not found; enough space for label; generalization is unlikely- space for label is available | N52: No | Q52: https://centrodedescargas.cnig.es/CentroDescargas/btn-poi
A53: =IF($B53="","",ROW()-1) -> 52 | B53: IGN | C53: IGN-04 | D53: =IF($C53="","",IFERROR(VLOOKUP($C53,Map_Register!$A$2:$C$5,3,FALSE()),"")) -> Toponym Labels | E53: Toponym | F53: 102433 | G53: Landscape | H53: Gainbeltz | I53: Basque | J53: Present | M53: labelled as landscape | Q53: https://centrodedescargas.cnig.es/CentroDescargas/btn-poi
A54: =IF($B54="","",ROW()-1) -> 53 | B54: IGN | C54: IGN-04 | D54: =IF($C54="","",IFERROR(VLOOKUP($C54,Map_Register!$A$2:$C$5,3,FALSE()),"")) -> Toponym Labels | E54: Toponym | F54: 102434 | G54: Landscape | H54: Unalbide | I54: Basque | J54: Present | M54: labelled as landscape | Q54: https://centrodedescargas.cnig.es/CentroDescargas/btn-poi
A55: =IF($B55="","",ROW()-1) -> 54 | B55: IGN | C55: IGN-04 | D55: =IF($C55="","",IFERROR(VLOOKUP($C55,Map_Register!$A$2:$C$5,3,FALSE()),"")) -> Toponym Labels | E55: Toponym | F55: 102435 | G55: Landscape | H55: Oianberri | I55: Basque | J55: Absent | K55: Yes | L55: No | M55: Label not found; enough space for label; generalization is unlikely- space for label is available | N55: No | Q55: https://centrodedescargas.cnig.es/CentroDescargas/btn-poi
A56: =IF($B56="","",ROW()-1) -> 55 | B56: IGN | C56: IGN-04 | D56: =IF($C56="","",IFERROR(VLOOKUP($C56,Map_Register!$A$2:$C$5,3,FALSE()),"")) -> Toponym Labels | E56: Toponym | F56: 102828 | G56: Landscape | H56: Korroskata | I56: Basque | J56: Absent | K56: Yes | L56: No | M56: Label not found; enough space for label; generalization is unlikely- space for label is available | N56: No | Q56: https://centrodedescargas.cnig.es/CentroDescargas/btn-poi
A57: =IF($B57="","",ROW()-1) -> 56 | B57: IGN | C57: IGN-04 | D57: =IF($C57="","",IFERROR(VLOOKUP($C57,Map_Register!$A$2:$C$5,3,FALSE()),"")) -> Toponym Labels | E57: Toponym | F57: 102829 | G57: Landscape | H57: Okalar | I57: Basque | J57: Present | M57: labelled as landscape | Q57: https://centrodedescargas.cnig.es/CentroDescargas/btn-poi
A58: =IF($B58="","",ROW()-1) -> 57 | B58: IGN | C58: IGN-04 | D58: =IF($C58="","",IFERROR(VLOOKUP($C58,Map_Register!$A$2:$C$5,3,FALSE()),"")) -> Toponym Labels | E58: Toponym | F58: 102830 | G58: Landscape | H58: Sarabe | I58: Basque | J58: Absent | K58: Yes | L58: No | M58: Label not found; enough space for label; generalization is unlikely- space for label is available | N58: No | Q58: https://centrodedescargas.cnig.es/CentroDescargas/btn-poi
A59: =IF($B59="","",ROW()-1) -> 58 | B59: IGN | C59: IGN-04 | D59: =IF($C59="","",IFERROR(VLOOKUP($C59,Map_Register!$A$2:$C$5,3,FALSE()),"")) -> Toponym Labels | E59: Toponym | F59: 102831 | G59: Landscape | H59: Morroko | I59: Basque | J59: Present | M59: labelled as landscape | Q59: https://centrodedescargas.cnig.es/CentroDescargas/btn-poi
A60: =IF($B60="","",ROW()-1) -> 59 | B60: IGN | C60: IGN-04 | D60: =IF($C60="","",IFERROR(VLOOKUP($C60,Map_Register!$A$2:$C$5,3,FALSE()),"")) -> Toponym Labels | E60: Toponym | F60: 102832 | G60: Landscape | H60: Alzate | I60: Basque | J60: Absent | K60: Yes | L60: No | M60: Label not found; enough space for label; generalization is unlikely- space for label is available | N60: No | Q60: https://centrodedescargas.cnig.es/CentroDescargas/btn-poi
A61: =IF($B61="","",ROW()-1) -> 60 | B61: IGN | C61: IGN-04 | D61: =IF($C61="","",IFERROR(VLOOKUP($C61,Map_Register!$A$2:$C$5,3,FALSE()),"")) -> Toponym Labels | E61: Toponym | F61: 102833 | G61: Landscape | H61: Sorotxo | I61: Basque | J61: Absent | K61: Yes | L61: No | M61: Label not found; enough space for label; generalization is unlikely- space for label is available | N61: No | Q61: https://centrodedescargas.cnig.es/CentroDescargas/btn-poi
A62: =IF($B62="","",ROW()-1) -> 61 | B62: IGN | C62: IGN-04 | D62: =IF($C62="","",IFERROR(VLOOKUP($C62,Map_Register!$A$2:$C$5,3,FALSE()),"")) -> Toponym Labels | E62: Toponym | F62: 102834 | G62: Landscape | H62: Buru-Gorri | I62: Basque | J62: Absent | K62: Yes | L62: No | M62: Label not found; enough space for label; generalization is unlikely- space for label is available | N62: No | Q62: https://centrodedescargas.cnig.es/CentroDescargas/btn-poi
A63: =IF($B63="","",ROW()-1) -> 62 | B63: IGN | C63: IGN-04 | D63: =IF($C63="","",IFERROR(VLOOKUP($C63,Map_Register!$A$2:$C$5,3,FALSE()),"")) -> Toponym Labels | E63: Toponym | F63: 102835 | G63: Landscape | H63: Iengo Meaka | I63: Basque | J63: Present | M63: labelled as landscape | Q63: https://centrodedescargas.cnig.es/CentroDescargas/btn-poi
A64: =IF($B64="","",ROW()-1) -> 63 | B64: IGN | C64: IGN-04 | D64: =IF($C64="","",IFERROR(VLOOKUP($C64,Map_Register!$A$2:$C$5,3,FALSE()),"")) -> Toponym Labels | E64: Toponym | F64: 102836 | G64: Landscape | H64: Erroizpe | I64: Basque | J64: Absent | K64: Yes | L64: No | M64: Label not found; enough space for label; generalization is unlikely- space for label is available | N64: No | Q64: https://centrodedescargas.cnig.es/CentroDescargas/btn-poi
A65: =IF($B65="","",ROW()-1) -> 64 | B65: IGN | C65: IGN-04 | D65: =IF($C65="","",IFERROR(VLOOKUP($C65,Map_Register!$A$2:$C$5,3,FALSE()),"")) -> Toponym Labels | E65: Toponym | F65: 102837 | G65: Landscape | H65: Biribilleta | I65: Basque | J65: Present | M65: labelled as landscape | Q65: https://centrodedescargas.cnig.es/CentroDescargas/btn-poi
A66: =IF($B66="","",ROW()-1) -> 65 | B66: IGN | C66: IGN-04 | D66: =IF($C66="","",IFERROR(VLOOKUP($C66,Map_Register!$A$2:$C$5,3,FALSE()),"")) -> Toponym Labels | E66: Toponym | F66: 102838 | G66: Landscape | H66: Biotegi | I66: Basque | J66: Absent | K66: Yes | L66: No | M66: Label not found; enough space for label; generalization is unlikely- space for label is available | N66: No | Q66: https://centrodedescargas.cnig.es/CentroDescargas/btn-poi
A67: =IF($B67="","",ROW()-1) -> 66 | B67: IGN | C67: IGN-04 | D67: =IF($C67="","",IFERROR(VLOOKUP($C67,Map_Register!$A$2:$C$5,3,FALSE()),"")) -> Toponym Labels | E67: Toponym | F67: 102839 | G67: Landscape | H67: Ledi | I67: Basque | J67: Present | M67: labelled as landscape | Q67: https://centrodedescargas.cnig.es/CentroDescargas/btn-poi
A68: =IF($B68="","",ROW()-1) -> 67 | B68: IGN | C68: IGN-04 | D68: =IF($C68="","",IFERROR(VLOOKUP($C68,Map_Register!$A$2:$C$5,3,FALSE()),"")) -> Toponym Labels | E68: Toponym | F68: 102840 | G68: Landscape | H68: Zerrimutur | I68: Basque | J68: Present | M68: labelled as landscape | Q68: https://centrodedescargas.cnig.es/CentroDescargas/btn-poi
A69: =IF($B69="","",ROW()-1) -> 68 | B69: IGN | C69: IGN-04 | D69: =IF($C69="","",IFERROR(VLOOKUP($C69,Map_Register!$A$2:$C$5,3,FALSE()),"")) -> Toponym Labels | E69: Toponym | F69: 102841 | G69: Landscape | H69: Berdabo-Etxala | I69: Basque | J69: Absent | K69: Yes | L69: No | M69: Label not found; enough space for label; generalization is unlikely- space for label is available | N69: No | Q69: https://centrodedescargas.cnig.es/CentroDescargas/btn-poi
A70: =IF($B70="","",ROW()-1) -> 69 | B70: IGN | C70: IGN-04 | D70: =IF($C70="","",IFERROR(VLOOKUP($C70,Map_Register!$A$2:$C$5,3,FALSE()),"")) -> Toponym Labels | E70: Toponym | F70: 102842 | G70: Landscape | H70: Malkorra | I70: Basque | J70: Present | M70: labelled as landscape | Q70: https://centrodedescargas.cnig.es/CentroDescargas/btn-poi
A71: =IF($B71="","",ROW()-1) -> 70 | B71: IGN | C71: IGN-04 | D71: =IF($C71="","",IFERROR(VLOOKUP($C71,Map_Register!$A$2:$C$5,3,FALSE()),"")) -> Toponym Labels | E71: Toponym | F71: 102843 | G71: Landscape | H71: Nekoitza | I71: Basque | J71: Present | M71: labelled as landscape | Q71: https://centrodedescargas.cnig.es/CentroDescargas/btn-poi
A72: =IF($B72="","",ROW()-1) -> 71 | B72: IGN | C72: IGN-04 | D72: =IF($C72="","",IFERROR(VLOOKUP($C72,Map_Register!$A$2:$C$5,3,FALSE()),"")) -> Toponym Labels | E72: Toponym | F72: 102844 | G72: Landscape | H72: Zokoia | I72: Basque | J72: Present | M72: labelled as landscape | Q72: https://centrodedescargas.cnig.es/CentroDescargas/btn-poi
A73: =IF($B73="","",ROW()-1) -> 72 | B73: IGN | C73: IGN-04 | D73: =IF($C73="","",IFERROR(VLOOKUP($C73,Map_Register!$A$2:$C$5,3,FALSE()),"")) -> Toponym Labels | E73: Toponym | F73: 102845 | G73: Landscape | H73: Loiola | I73: Basque | J73: Present | M73: labelled as landscape | Q73: https://centrodedescargas.cnig.es/CentroDescargas/btn-poi
A74: =IF($B74="","",ROW()-1) -> 73 | B74: IGN | C74: IGN-04 | D74: =IF($C74="","",IFERROR(VLOOKUP($C74,Map_Register!$A$2:$C$5,3,FALSE()),"")) -> Toponym Labels | E74: Toponym | F74: 102846 | G74: Landscape | H74: San Antón | I74: Basque | J74: Absent | K74: Yes | L74: No | M74: Label not found; enough space for label; generalization is unlikely- space for label is available | N74: No | Q74: https://centrodedescargas.cnig.es/CentroDescargas/btn-poi
A75: =IF($B75="","",ROW()-1) -> 74 | B75: IGN | C75: IGN-04 | D75: =IF($C75="","",IFERROR(VLOOKUP($C75,Map_Register!$A$2:$C$5,3,FALSE()),"")) -> Toponym Labels | E75: Toponym | F75: 102847 | G75: Landscape | H75: Alduzin-Barrutia | I75: Basque | J75: Absent | K75: Yes | L75: No | M75: Label not found; enough space for label; generalization is unlikely- space for label is available | N75: No | Q75: https://centrodedescargas.cnig.es/CentroDescargas/btn-poi
A76: =IF($B76="","",ROW()-1) -> 75 | B76: IGN | C76: IGN-04 | D76: =IF($C76="","",IFERROR(VLOOKUP($C76,Map_Register!$A$2:$C$5,3,FALSE()),"")) -> Toponym Labels | E76: Toponym | F76: 102848 | G76: Landscape | H76: Alduzin-Mendi | I76: Basque | J76: Absent | K76: Yes | L76: No | M76: Label not found; enough space for label; generalization is unlikely- space for label is available | N76: No | Q76: https://centrodedescargas.cnig.es/CentroDescargas/btn-poi
A77: =IF($B77="","",ROW()-1) -> 76 | B77: IGN | C77: IGN-04 | D77: =IF($C77="","",IFERROR(VLOOKUP($C77,Map_Register!$A$2:$C$5,3,FALSE()),"")) -> Toponym Labels | E77: Toponym | F77: 102849 | G77: Landscape | H77: Unitzaraz | I77: Basque | J77: Present | M77: labelled as landscape | Q77: https://centrodedescargas.cnig.es/CentroDescargas/btn-poi
A78: =IF($B78="","",ROW()-1) -> 77 | B78: IGN | C78: IGN-04 | D78: =IF($C78="","",IFERROR(VLOOKUP($C78,Map_Register!$A$2:$C$5,3,FALSE()),"")) -> Toponym Labels | E78: Toponym | F78: 102850 | G78: Landscape | H78: Soroaundi | I78: Basque | J78: Present | M78: labelled as landscape | Q78: https://centrodedescargas.cnig.es/CentroDescargas/btn-poi
A79: =IF($B79="","",ROW()-1) -> 78 | B79: IGN | C79: IGN-04 | D79: =IF($C79="","",IFERROR(VLOOKUP($C79,Map_Register!$A$2:$C$5,3,FALSE()),"")) -> Toponym Labels | E79: Toponym | F79: 102851 | G79: Landscape | H79: Pagotxorri | I79: Basque | J79: Absent | K79: Yes | L79: No | M79: No name found | N79: No | Q79: https://centrodedescargas.cnig.es/CentroDescargas/btn-poi
A80: =IF($B80="","",ROW()-1) -> 79 | B80: IGN | C80: IGN-04 | D80: =IF($C80="","",IFERROR(VLOOKUP($C80,Map_Register!$A$2:$C$5,3,FALSE()),"")) -> Toponym Labels | E80: Toponym | F80: 102852 | G80: Landscape | H80: Sagozar | I80: Basque | J80: Absent | K80: Yes | L80: No | M80: Label not found; enough space for label; generalization is unlikely- space for label is available | N80: No | Q80: https://centrodedescargas.cnig.es/CentroDescargas/btn-poi
A81: =IF($B81="","",ROW()-1) -> 80 | B81: IGN | C81: IGN-04 | D81: =IF($C81="","",IFERROR(VLOOKUP($C81,Map_Register!$A$2:$C$5,3,FALSE()),"")) -> Toponym Labels | E81: Toponym | F81: 102853 | G81: Landscape | H81: Arramaleta | I81: Basque | J81: Present | M81: labelled as landscape | Q81: https://centrodedescargas.cnig.es/CentroDescargas/btn-poi
A82: =IF($B82="","",ROW()-1) -> 81 | B82: IGN | C82: IGN-04 | D82: =IF($C82="","",IFERROR(VLOOKUP($C82,Map_Register!$A$2:$C$5,3,FALSE()),"")) -> Toponym Labels | E82: Toponym | F82: 102854 | G82: Landscape | H82: Erroitza | I82: Basque | J82: Present | M82: Present | Q82: https://centrodedescargas.cnig.es/CentroDescargas/btn-poi
A83: =IF($B83="","",ROW()-1) -> 82 | B83: IGN | C83: IGN-04 | D83: =IF($C83="","",IFERROR(VLOOKUP($C83,Map_Register!$A$2:$C$5,3,FALSE()),"")) -> Toponym Labels | E83: Toponym | F83: 102855 | G83: Landscape | H83: Pagolleta-Malda | I83: Basque | J83: Absent | K83: Yes | L83: No | M83: Label not found; enough space for label; generalization is unlikely- space for label is available | N83: No | Q83: https://centrodedescargas.cnig.es/CentroDescargas/btn-poi
A84: =IF($B84="","",ROW()-1) -> 83 | B84: IGN | C84: IGN-04 | D84: =IF($C84="","",IFERROR(VLOOKUP($C84,Map_Register!$A$2:$C$5,3,FALSE()),"")) -> Toponym Labels | E84: Toponym | F84: 102856 | G84: Landscape | H84: Bidemakuta | I84: Basque | J84: Absent | K84: Yes | L84: No | M84: Label not found; enough space for label; generalization is unlikely- space for label is available | N84: No | Q84: https://centrodedescargas.cnig.es/CentroDescargas/btn-poi
A85: =IF($B85="","",ROW()-1) -> 84 | B85: IGN | C85: IGN-04 | D85: =IF($C85="","",IFERROR(VLOOKUP($C85,Map_Register!$A$2:$C$5,3,FALSE()),"")) -> Toponym Labels | E85: Toponym | F85: 103243 | G85: Landscape | H85: Errotarita | I85: Basque | J85: Absent | K85: Yes | L85: No | M85: Label not found; enough space for label; generalization is unlikely- space for label is available | N85: No | Q85: https://centrodedescargas.cnig.es/CentroDescargas/btn-poi
A86: =IF($B86="","",ROW()-1) -> 85 | B86: IGN | C86: IGN-04 | D86: =IF($C86="","",IFERROR(VLOOKUP($C86,Map_Register!$A$2:$C$5,3,FALSE()),"")) -> Toponym Labels | E86: Toponym | F86: 103245 | G86: Landscape | H86: Buarrin | I86: Basque | J86: Present | M86: labelled as landscape | Q86: https://centrodedescargas.cnig.es/CentroDescargas/btn-poi
A87: =IF($B87="","",ROW()-1) -> 86 | B87: IGN | C87: IGN-04 | D87: =IF($C87="","",IFERROR(VLOOKUP($C87,Map_Register!$A$2:$C$5,3,FALSE()),"")) -> Toponym Labels | E87: Toponym | F87: 103246 | G87: Landscape | H87: Usanbelarreta | I87: Basque | J87: Absent | K87: Yes | L87: No | M87: Label not found; enough space for label; generalization is unlikely- space for label is available | N87: No | Q87: https://centrodedescargas.cnig.es/CentroDescargas/btn-poi
A88: =IF($B88="","",ROW()-1) -> 87 | B88: IGN | C88: IGN-04 | D88: =IF($C88="","",IFERROR(VLOOKUP($C88,Map_Register!$A$2:$C$5,3,FALSE()),"")) -> Toponym Labels | E88: Toponym | F88: 103247 | G88: Landscape | H88: Izuko-Gana | I88: Basque | J88: Present | M88: labelled as landscape | Q88: https://centrodedescargas.cnig.es/CentroDescargas/btn-poi
A89: =IF($B89="","",ROW()-1) -> 88 | B89: IGN | C89: IGN-04 | D89: =IF($C89="","",IFERROR(VLOOKUP($C89,Map_Register!$A$2:$C$5,3,FALSE()),"")) -> Toponym Labels | E89: Toponym | F89: 103248 | G89: Landscape | H89: Borota | I89: Basque | J89: Absent | K89: Yes | L89: No | M89: Label not found; enough space for label; generalization is unlikely- space for label is available | N89: No | Q89: https://centrodedescargas.cnig.es/CentroDescargas/btn-poi
A90: =IF($B90="","",ROW()-1) -> 89 | B90: IGN | C90: IGN-04 | D90: =IF($C90="","",IFERROR(VLOOKUP($C90,Map_Register!$A$2:$C$5,3,FALSE()),"")) -> Toponym Labels | E90: Toponym | F90: 103249 | G90: Landscape | H90: Burkalleku | I90: Basque | J90: Present | M90: labelled as landscape | Q90: https://centrodedescargas.cnig.es/CentroDescargas/btn-poi
A91: =IF($B91="","",ROW()-1) -> 90 | B91: IGN | C91: IGN-04 | D91: =IF($C91="","",IFERROR(VLOOKUP($C91,Map_Register!$A$2:$C$5,3,FALSE()),"")) -> Toponym Labels | E91: Toponym | F91: 103250 | G91: Landscape | H91: Maradi | I91: Basque | J91: Present | M91: Larrain Maradi??? | Q91: https://centrodedescargas.cnig.es/CentroDescargas/btn-poi
A92: =IF($B92="","",ROW()-1) -> 91 | B92: IGN | C92: IGN-04 | D92: =IF($C92="","",IFERROR(VLOOKUP($C92,Map_Register!$A$2:$C$5,3,FALSE()),"")) -> Toponym Labels | E92: Toponym | F92: 103624 | G92: Landscape | H92: Udi-Azpie | I92: Basque | J92: Present | M92: labelled as landscape | Q92: https://centrodedescargas.cnig.es/CentroDescargas/btn-poi
A93: =IF($B93="","",ROW()-1) -> 92 | B93: IGN | C93: IGN-04 | D93: =IF($C93="","",IFERROR(VLOOKUP($C93,Map_Register!$A$2:$C$5,3,FALSE()),"")) -> Toponym Labels | E93: Toponym | F93: 103633 | G93: Landscape | H93: Erroiarri | I93: Basque | J93: Present | M93: labelled as landscape | Q93: https://centrodedescargas.cnig.es/CentroDescargas/btn-poi
A94: =IF($B94="","",ROW()-1) -> 93 | B94: IGN | C94: IGN-04 | D94: =IF($C94="","",IFERROR(VLOOKUP($C94,Map_Register!$A$2:$C$5,3,FALSE()),"")) -> Toponym Labels | E94: Toponym | F94: 103634 | G94: Landscape | H94: Argarate | I94: Basque | J94: Present | M94: labelled as landscape | Q94: https://centrodedescargas.cnig.es/CentroDescargas/btn-poi
A95: =IF($B95="","",ROW()-1) -> 94 | B95: IGN | C95: IGN-04 | D95: =IF($C95="","",IFERROR(VLOOKUP($C95,Map_Register!$A$2:$C$5,3,FALSE()),"")) -> Toponym Labels | E95: Toponym | F95: 103635 | G95: Landscape | H95: Mayo-Lepo | I95: Basque | J95: Absent | K95: Yes | L95: No | M95: Label not found; enough space for label; generalization is unlikely- space for label is available | N95: No | Q95: https://centrodedescargas.cnig.es/CentroDescargas/btn-poi
A96: =IF($B96="","",ROW()-1) -> 95 | B96: IGN | C96: IGN-04 | D96: =IF($C96="","",IFERROR(VLOOKUP($C96,Map_Register!$A$2:$C$5,3,FALSE()),"")) -> Toponym Labels | E96: Toponym | F96: 103637 | G96: Landscape | H96: Elizmendi | I96: Basque | J96: Present | M96: labelled as landscape | Q96: https://centrodedescargas.cnig.es/CentroDescargas/btn-poi
A97: =IF($B97="","",ROW()-1) -> 96 | B97: IGN | C97: IGN-04 | D97: =IF($C97="","",IFERROR(VLOOKUP($C97,Map_Register!$A$2:$C$5,3,FALSE()),"")) -> Toponym Labels | E97: Toponym | F97: 103639 | G97: Landscape | H97: Undaidine | I97: Basque | J97: Present | M97: labelled as landscape | Q97: https://centrodedescargas.cnig.es/CentroDescargas/btn-poi
A98: =IF($B98="","",ROW()-1) -> 97 | B98: IGN | C98: IGN-04 | D98: =IF($C98="","",IFERROR(VLOOKUP($C98,Map_Register!$A$2:$C$5,3,FALSE()),"")) -> Toponym Labels | E98: Toponym | F98: 103640 | G98: Landscape | H98: Urrizti | I98: Basque | J98: Present | M98: labelled as landscape | Q98: https://centrodedescargas.cnig.es/CentroDescargas/btn-poi
A99: =IF($B99="","",ROW()-1) -> 98 | B99: IGN | C99: IGN-04 | D99: =IF($C99="","",IFERROR(VLOOKUP($C99,Map_Register!$A$2:$C$5,3,FALSE()),"")) -> Toponym Labels | E99: Toponym | F99: 103641 | G99: Landscape | H99: Basakundi | I99: Basque | J99: Absent | K99: Yes | L99: No | M99: Label not found; enough space for label; generalization is unlikely- space for label is available | N99: No | Q99: https://centrodedescargas.cnig.es/CentroDescargas/btn-poi
A100: =IF($B100="","",ROW()-1) -> 99 | B100: IGN | C100: IGN-04 | D100: =IF($C100="","",IFERROR(VLOOKUP($C100,Map_Register!$A$2:$C$5,3,FALSE()),"")) -> Toponym Labels | E100: Toponym | F100: 112568 | G100: Landscape | H100: Arribeltza | I100: Basque | J100: Present | M100: labelled as landscape | Q100: https://centrodedescargas.cnig.es/CentroDescargas/btn-poi
...

Sheet Spain_Culture
A1: Record_ID | B1: NMA | C1: Map_ID | D1: Sheet_Type | E1: Category | F1: FID | G1: Feature_Type | H1: Name(If Available) | I1: Code | J1: RenderingStage_Flag | K1: Generalization_Flag | L1: Justification | M1: Specification_Flag | N1: Feature_Count | O1: Bertin_Variable | P1: Reference_Source
A2: =IF($B2="","",ROW()-1) -> 1 | B2: IGN | C2: IGN-02 | D2: =IF($C2="","",IFERROR(VLOOKUP($C2,Map_Register!$A$2:$C$5,3,FALSE()),"")) -> Cultural Heritage Area | E2: Cultural | F2: 170 | G2: Conjunto histórico | H2: Conjunto Histórico de Sevilla | I2: Absent | J2: Yes | K2: No | L2: no label or symbol found | M2: No | P2: https://centrodedescargas.cnig.es/CentroDescargas/detalleArchivo?sec=12165696
A3: =IF($B3="","",ROW()-1) -> 2 | B3: IGN | C3: IGN-02 | D3: =IF($C3="","",IFERROR(VLOOKUP($C3,Map_Register!$A$2:$C$5,3,FALSE()),"")) -> Cultural Heritage Area | E3: Cultural | F3: 239 | G3: Monumento | H3: Monte Gurugú | I3: Absent | J3: Yes | K3: Yes | L3: green area, no monument symbol | M3: No | P3: https://centrodedescargas.cnig.es/CentroDescargas/detalleArchivo?sec=12165697
A4: =IF($B4="","",ROW()-1) -> 3 | B4: IGN | C4: IGN-02 | D4: =IF($C4="","",IFERROR(VLOOKUP($C4,Map_Register!$A$2:$C$5,3,FALSE()),"")) -> Cultural Heritage Area | E4: Cultural | F4: 529 | G4: Monumento | H4: Estatua de Bécquer | I4: Absent | J4: Yes | K4: Yes | L4: statue seems to be small | M4: No | P4: https://centrodedescargas.cnig.es/CentroDescargas/detalleArchivo?sec=12165698
A5: =IF($B5="","",ROW()-1) -> 4 | B5: IGN | C5: IGN-02 | D5: =IF($C5="","",IFERROR(VLOOKUP($C5,Map_Register!$A$2:$C$5,3,FALSE()),"")) -> Cultural Heritage Area | E5: Cultural | F5: 586 | G5: Monumento | H5: Airbus | I5: Absent | J5: Yes | K5: Yes | L5: most likely due to size | M5: No | P5: https://centrodedescargas.cnig.es/CentroDescargas/detalleArchivo?sec=12165699
A6: =IF($B6="","",ROW()-1) -> 5 | B6: IGN | C6: IGN-02 | D6: =IF($C6="","",IFERROR(VLOOKUP($C6,Map_Register!$A$2:$C$5,3,FALSE()),"")) -> Cultural Heritage Area | E6: Cultural | F6: 587 | G6: Monumento | H6: Monumento a Simón Bolívar | I6: Absent | J6: Yes | K6: Yes | L6: statue monument | M6: No | P6: https://centrodedescargas.cnig.es/CentroDescargas/detalleArchivo?sec=12165700
A7: =IF($B7="","",ROW()-1) -> 6 | B7: IGN | C7: IGN-02 | D7: =IF($C7="","",IFERROR(VLOOKUP($C7,Map_Register!$A$2:$C$5,3,FALSE()),"")) -> Cultural Heritage Area | E7: Cultural | F7: 588 | G7: Monumento | H7: Monumento a Juan Sebastián Elcano | I7: Absent | J7: Yes | K7: Yes | L7: most likely due to size ; since it’s a small monument(statue) | M7: No | P7: https://centrodedescargas.cnig.es/CentroDescargas/detalleArchivo?sec=12165701
A8: =IF($B8="","",ROW()-1) -> 7 | B8: IGN | C8: IGN-02 | D8: =IF($C8="","",IFERROR(VLOOKUP($C8,Map_Register!$A$2:$C$5,3,FALSE()),"")) -> Cultural Heritage Area | E8: Cultural | F8: 589 | G8: Monumento | H8: Triunfo del Corazón de María | I8: Absent | J8: Yes | K8: Yes | L8: most likely due to size ; since it’s a small monument(statue) | M8: No | P8: https://centrodedescargas.cnig.es/CentroDescargas/detalleArchivo?sec=12165702
A9: =IF($B9="","",ROW()-1) -> 8 | B9: IGN | C9: IGN-02 | D9: =IF($C9="","",IFERROR(VLOOKUP($C9,Map_Register!$A$2:$C$5,3,FALSE()),"")) -> Cultural Heritage Area | E9: Cultural | F9: 594 | G9: Monumento | H9: Monumento a Juan Manuel Rodríguez Ojeda | I9: Absent | J9: Yes | K9: Yes | L9: size | M9: No | P9: https://centrodedescargas.cnig.es/CentroDescargas/detalleArchivo?sec=12165703
A10: =IF($B10="","",ROW()-1) -> 9 | B10: IGN | C10: IGN-02 | D10: =IF($C10="","",IFERROR(VLOOKUP($C10,Map_Register!$A$2:$C$5,3,FALSE()),"")) -> Cultural Heritage Area | E10: Cultural | F10: 595 | G10: Monumento | H10: Cohete Ariane 4 | I10: Absent | J10: Yes | K10: Yes | L10: size | M10: No | P10: https://centrodedescargas.cnig.es/CentroDescargas/detalleArchivo?sec=12165704
A11: =IF($B11="","",ROW()-1) -> 10 | B11: IGN | C11: IGN-02 | D11: =IF($C11="","",IFERROR(VLOOKUP($C11,Map_Register!$A$2:$C$5,3,FALSE()),"")) -> Cultural Heritage Area | E11: Cultural | F11: 597 | G11: Monumento | H11: Antena Instituto de Astrofísica de Canarias Expo 92 | I11: Absent | J11: Yes | K11: Yes | L11: size | M11: No | P11: https://centrodedescargas.cnig.es/CentroDescargas/detalleArchivo?sec=12165705
A12: =IF($B12="","",ROW()-1) -> 11 | B12: IGN | C12: IGN-02 | D12: =IF($C12="","",IFERROR(VLOOKUP($C12,Map_Register!$A$2:$C$5,3,FALSE()),"")) -> Cultural Heritage Area | E12: Cultural | F12: 613 | G12: Monumento | H12: Avión Saeta | I12: Present | L12: historic wall | P12: https://centrodedescargas.cnig.es/CentroDescargas/detalleArchivo?sec=12165706
A13: =IF($B13="","",ROW()-1) -> 12 | B13: IGN | C13: IGN-02 | D13: =IF($C13="","",IFERROR(VLOOKUP($C13,Map_Register!$A$2:$C$5,3,FALSE()),"")) -> Cultural Heritage Area | E13: Cultural | F13: 614 | G13: Monumento | H13: Monumento al Sagrado Corazón de Jesús | I13: Absent | J13: Yes | K13: Yes | L13: empty space, no symbol for monument | M13: No | P13: https://centrodedescargas.cnig.es/CentroDescargas/detalleArchivo?sec=12165707
A14: =IF($B14="","",ROW()-1) -> 13 | B14: IGN | C14: IGN-02 | D14: =IF($C14="","",IFERROR(VLOOKUP($C14,Map_Register!$A$2:$C$5,3,FALSE()),"")) -> Cultural Heritage Area | E14: Cultural | F14: 615 | G14: Monumento | H14: Lugar del Fusilamiento de Blas Infante | I14: Absent | J14: Yes | K14: Yes | L14: size | M14: No | P14: https://centrodedescargas.cnig.es/CentroDescargas/detalleArchivo?sec=12165708
A15: =IF($B15="","",ROW()-1) -> 14 | B15: IGN | C15: IGN-02 | D15: =IF($C15="","",IFERROR(VLOOKUP($C15,Map_Register!$A$2:$C$5,3,FALSE()),"")) -> Cultural Heritage Area | E15: Cultural | F15: 678 | G15: Monumento | H15: Monumento a Cristóbal Colón | I15: Absent | J15: Yes | K15: Yes | L15: most likely due to size ; since it’s a small monument(statue) | M15: No | P15: https://centrodedescargas.cnig.es/CentroDescargas/detalleArchivo?sec=12165709
A16: =IF($B16="","",ROW()-1) -> 15 | B16: IGN | C16: IGN-02 | D16: =IF($C16="","",IFERROR(VLOOKUP($C16,Map_Register!$A$2:$C$5,3,FALSE()),"")) -> Cultural Heritage Area | E16: Cultural | F16: 679 | G16: Monumento | H16: Estatua Aníbal González | I16: Absent | J16: Yes | K16: Yes | L16: most likely due to size ; since it’s a small monument(statue) | M16: No | P16: https://centrodedescargas.cnig.es/CentroDescargas/detalleArchivo?sec=12165710
A17: =IF($B17="","",ROW()-1) -> 16 | B17: IGN | C17: IGN-02 | D17: =IF($C17="","",IFERROR(VLOOKUP($C17,Map_Register!$A$2:$C$5,3,FALSE()),"")) -> Cultural Heritage Area | E17: Cultural | F17: 680 | G17: Monumento | H17: Monumento al Cid Campeador | I17: Absent | J17: Yes | K17: Yes | L17: size | M17: No | P17: https://centrodedescargas.cnig.es/CentroDescargas/detalleArchivo?sec=12165711
A18: =IF($B18="","",ROW()-1) -> 17 | B18: IGN | C18: IGN-02 | D18: =IF($C18="","",IFERROR(VLOOKUP($C18,Map_Register!$A$2:$C$5,3,FALSE()),"")) -> Cultural Heritage Area | E18: Cultural | F18: 681 | G18: Monumento | H18: Piedra Llorosa | I18: Absent | J18: Yes | K18: Yes | L18: size | M18: No | P18: https://centrodedescargas.cnig.es/CentroDescargas/detalleArchivo?sec=12165712
A19: =IF($B19="","",ROW()-1) -> 18 | B19: IGN | C19: IGN-02 | D19: =IF($C19="","",IFERROR(VLOOKUP($C19,Map_Register!$A$2:$C$5,3,FALSE()),"")) -> Cultural Heritage Area | E19: Cultural | F19: 682 | G19: Monumento | H19: Réplica del Giraldillo | I19: Absent | J19: Yes | K19: Yes | L19: most likely due to size ; since it’s a small monument(statue) | M19: No | P19: https://centrodedescargas.cnig.es/CentroDescargas/detalleArchivo?sec=12165713
A20: =IF($B20="","",ROW()-1) -> 19 | B20: IGN | C20: IGN-02 | D20: =IF($C20="","",IFERROR(VLOOKUP($C20,Map_Register!$A$2:$C$5,3,FALSE()),"")) -> Cultural Heritage Area | E20: Cultural | F20: 683 | G20: Monumento | H20: Monumento a la Inmaculada Concepción | I20: Absent | J20: Yes | K20: Yes | L20: size | M20: No | P20: https://centrodedescargas.cnig.es/CentroDescargas/detalleArchivo?sec=12165714
A21: =IF($B21="","",ROW()-1) -> 20 | B21: IGN | C21: IGN-02 | D21: =IF($C21="","",IFERROR(VLOOKUP($C21,Map_Register!$A$2:$C$5,3,FALSE()),"")) -> Cultural Heritage Area | E21: Cultural | F21: 3049 | G21: Muralla | H21: Muralla de la Macarena | I21: Present | L21: historic wall | P21: https://centrodedescargas.cnig.es/CentroDescargas/detalleArchivo?sec=12165715
A22: =IF($B22="","",ROW()-1) -> 21 | B22: IGN | C22: IGN-02 | D22: =IF($C22="","",IFERROR(VLOOKUP($C22,Map_Register!$A$2:$C$5,3,FALSE()),"")) -> Cultural Heritage Area | E22: Cultural | F22: 3050 | G22: Muralla | H22: Murallas de San Juan | I22: Present | L22: historical wall | P22: https://centrodedescargas.cnig.es/CentroDescargas/detalleArchivo?sec=12165716
A23: =IF($B23="","",ROW()-1) -> 22 | B23: IGN | C23: IGN-02 | D23: =IF($C23="","",IFERROR(VLOOKUP($C23,Map_Register!$A$2:$C$5,3,FALSE()),"")) -> Cultural Heritage Area | E23: Cultural | F23: 4378 | G23: Fortaleza/castillo | H23: Castillo de Alcalá de Guadaíra | I23: Present | L23: castle symbolized by historic walls | P23: https://centrodedescargas.cnig.es/CentroDescargas/detalleArchivo?sec=12165717
A24: =IF($B24="","",ROW()-1) -> 23 | B24: IGN | C24: IGN-02 | D24: =IF($C24="","",IFERROR(VLOOKUP($C24,Map_Register!$A$2:$C$5,3,FALSE()),"")) -> Cultural Heritage Area | E24: Cultural | F24: 6751 | G24: Restos arqueológicos | H24: Dolmen de Montelirio | I24: Present | L24: archeological site | P24: https://centrodedescargas.cnig.es/CentroDescargas/detalleArchivo?sec=12165718
A25: =IF($B25="","",ROW()-1) -> 24 | B25: IGN | C25: IGN-02 | D25: =IF($C25="","",IFERROR(VLOOKUP($C25,Map_Register!$A$2:$C$5,3,FALSE()),"")) -> Cultural Heritage Area | E25: Cultural | F25: 6752 | G25: Restos arqueológicos | H25: Yacimiento Arqueológico del Carambolo | I25: Present | L25: archaeological remains | P25: https://centrodedescargas.cnig.es/CentroDescargas/detalleArchivo?sec=12165719
A26: =IF($B26="","",ROW()-1) -> 25 | B26: IGN | C26: IGN-02 | D26: =IF($C26="","",IFERROR(VLOOKUP($C26,Map_Register!$A$2:$C$5,3,FALSE()),"")) -> Cultural Heritage Area | E26: Cultural | F26: 6766 | G26: Restos arqueológicos | H26: Dolmen de Matarrubilla | I26: Present | L26: archaeological remains | P26: https://centrodedescargas.cnig.es/CentroDescargas/detalleArchivo?sec=12165720
A27: =IF($B27="","",ROW()-1) -> 26 | B27: IGN | C27: IGN-02 | D27: =IF($C27="","",IFERROR(VLOOKUP($C27,Map_Register!$A$2:$C$5,3,FALSE()),"")) -> Cultural Heritage Area | E27: Cultural | F27: 6768 | G27: Restos arqueológicos | H27: Dolmen de la Pastora | I27: Present | L27: archeological site | P27: https://centrodedescargas.cnig.es/CentroDescargas/detalleArchivo?sec=12165721
A28: =IF($B28="","",ROW()-1) -> 27 | B28: IGN | C28: IGN-02 | D28: =IF($C28="","",IFERROR(VLOOKUP($C28,Map_Register!$A$2:$C$5,3,FALSE()),"")) -> Cultural Heritage Area | E28: Cultural | F28: 7298 | G28: Restos arqueológicos | H28: Conjunto Arqueológico de Itálica | I28: Present | L28: archaeological remains; label presen | P28: https://centrodedescargas.cnig.es/CentroDescargas/detalleArchivo?sec=12165722
A29: =IF($B29="","",ROW()-1) -> 28 | B29: IGN | C29: IGN-02 | D29: =IF($C29="","",IFERROR(VLOOKUP($C29,Map_Register!$A$2:$C$5,3,FALSE()),"")) -> Cultural Heritage Area | E29: Cultural | F29: 19129 | G29: Muralla | H29: Muralla de Itálica | I29: Present | L29: historical wall | P29: https://centrodedescargas.cnig.es/CentroDescargas/detalleArchivo?sec=12165723
A30: =IF($B30="","",ROW()-1) -> 29 | B30: IGN | C30: IGN-02 | D30: =IF($C30="","",IFERROR(VLOOKUP($C30,Map_Register!$A$2:$C$5,3,FALSE()),"")) -> Cultural Heritage Area | E30: Cultural | F30: 19131 | G30: Monumento | H30: Monumento a Andalucía | I30: Absent | J30: Yes | K30: Yes | L30: empty space, no symbol for monument | M30: No | P30: https://centrodedescargas.cnig.es/CentroDescargas/detalleArchivo?sec=12165724
A31: =IF($B31="","",ROW()-1) -> 30 | B31: IGN | C31: IGN-02 | D31: =IF($C31="","",IFERROR(VLOOKUP($C31,Map_Register!$A$2:$C$5,3,FALSE()),"")) -> Cultural Heritage Area | E31: Cultural | F31: 19272 | G31: Restos arqueológicos | H31: Casa de Cañada Honda | I31: Present | L31: arch site | P31: https://centrodedescargas.cnig.es/CentroDescargas/detalleArchivo?sec=12165725
A32: =IF($B32="","",ROW()-1) -> 31 | B32: IGN | C32: IGN-02 | D32: =IF($C32="","",IFERROR(VLOOKUP($C32,Map_Register!$A$2:$C$5,3,FALSE()),"")) -> Cultural Heritage Area | E32: Cultural | F32: 20065 | G32: Restos arqueológicos | H32: Casa del Planetario | I32: Present | L32: archaeological remains | P32: https://centrodedescargas.cnig.es/CentroDescargas/detalleArchivo?sec=12165726
A33: =IF($B33="","",ROW()-1) -> 32 | B33: IGN | C33: IGN-02 | D33: =IF($C33="","",IFERROR(VLOOKUP($C33,Map_Register!$A$2:$C$5,3,FALSE()),"")) -> Cultural Heritage Area | E33: Cultural | F33: 25511 | G33: Monumento | H33: Estatua a El Bombita | I33: Absent | J33: Yes | K33: Yes | L33: size | M33: No | P33: https://centrodedescargas.cnig.es/CentroDescargas/detalleArchivo?sec=12165727
A34: =IF($B34="","",ROW()-1) -> 33 | B34: IGN | C34: IGN-02 | D34: =IF($C34="","",IFERROR(VLOOKUP($C34,Map_Register!$A$2:$C$5,3,FALSE()),"")) -> Cultural Heritage Area | E34: Cultural | F34: 27083 | G34: Monumento | H34: Monumento a los Marineros Voluntarios | I34: Absent | J34: Yes | K34: Yes | L34: size | M34: No | P34: https://centrodedescargas.cnig.es/CentroDescargas/detalleArchivo?sec=12165728
A35: =IF($B35="","",ROW()-1) -> 34 | B35: IGN | C35: IGN-02 | D35: =IF($C35="","",IFERROR(VLOOKUP($C35,Map_Register!$A$2:$C$5,3,FALSE()),"")) -> Cultural Heritage Area | E35: Cultural | F35: 27086 | G35: Monumento | H35: El Lápiz | I35: Absent | J35: Yes | K35: Yes | L35: size | M35: No | P35: https://centrodedescargas.cnig.es/CentroDescargas/detalleArchivo?sec=12165729
A36: =IF($B36="","",ROW()-1) -> 35 | B36: IGN | C36: IGN-02 | D36: =IF($C36="","",IFERROR(VLOOKUP($C36,Map_Register!$A$2:$C$5,3,FALSE()),"")) -> Cultural Heritage Area | E36: Cultural | F36: 27087 | G36: Monumento | H36: Monumento Columnas de Hércules | I36: Absent | J36: Yes | K36: Yes | L36: size | M36: No | P36: https://centrodedescargas.cnig.es/CentroDescargas/detalleArchivo?sec=12165730
A37: =IF($B37="","",ROW()-1) -> 36 | B37: IGN | C37: IGN-02 | D37: =IF($C37="","",IFERROR(VLOOKUP($C37,Map_Register!$A$2:$C$5,3,FALSE()),"")) -> Cultural Heritage Area | E37: Cultural | F37: 27088 | G37: Monumento | H37: Estatua San Juan Bautista de la Salle | I37: Absent | J37: Yes | K37: Yes | L37: size | M37: No | P37: https://centrodedescargas.cnig.es/CentroDescargas/detalleArchivo?sec=12165731
A38: =IF($B38="","",ROW()-1) -> 37 | B38: IGN | C38: IGN-02 | D38: =IF($C38="","",IFERROR(VLOOKUP($C38,Map_Register!$A$2:$C$5,3,FALSE()),"")) -> Cultural Heritage Area | E38: Cultural | F38: 28207 | G38: Monumento | H38: Atomium | I38: Absent | J38: Yes | K38: Yes | L38: most likely due to size ; since it’s a small monument(statue) | M38: No | P38: https://centrodedescargas.cnig.es/CentroDescargas/detalleArchivo?sec=12165732
A39: =IF($B39="","",ROW()-1) -> 38 | B39: IGN | C39: IGN-02 | D39: =IF($C39="","",IFERROR(VLOOKUP($C39,Map_Register!$A$2:$C$5,3,FALSE()),"")) -> Cultural Heritage Area | E39: Cultural | F39: 38477 | G39: Monumento | H39: Monumento a Santa Ángela de la Cruz | I39: Absent | J39: Yes | K39: Yes | L39: most likely due to size ; since it’s a small monument(statue) | M39: No | P39: https://centrodedescargas.cnig.es/CentroDescargas/detalleArchivo?sec=12165733
A40: =IF($B40="","",ROW()-1) -> 39 | B40: IGN | C40: IGN-02 | D40: =IF($C40="","",IFERROR(VLOOKUP($C40,Map_Register!$A$2:$C$5,3,FALSE()),"")) -> Cultural Heritage Area | E40: Cultural | F40: 38719 | G40: Monumento | H40: Puerta del Perdón | I40: Absent | J40: Yes | K40: Yes | L40: part of building | M40: No | P40: https://centrodedescargas.cnig.es/CentroDescargas/detalleArchivo?sec=12165734
A41: =IF($B41="","",ROW()-1) -> 40 | B41: IGN | C41: IGN-02 | D41: =IF($C41="","",IFERROR(VLOOKUP($C41,Map_Register!$A$2:$C$5,3,FALSE()),"")) -> Cultural Heritage Area | E41: Cultural | F41: 38723 | G41: Museo | H41: Centro Cerámica Triana | I41: Absent | J41: Yes | K41: Yes | L41: location falls on a generalized building rendered as general building ; but no indication of it being a museum | M41: No | P41: https://centrodedescargas.cnig.es/CentroDescargas/detalleArchivo?sec=12165735
A42: =IF($B42="","",ROW()-1) -> 41 | B42: IGN | C42: IGN-02 | D42: =IF($C42="","",IFERROR(VLOOKUP($C42,Map_Register!$A$2:$C$5,3,FALSE()),"")) -> Cultural Heritage Area | E42: Cultural | F42: 40904 | G42: Restos arqueológicos | H42: Teatro Romano de Itálica | I42: Present | L42: arch site | P42: https://centrodedescargas.cnig.es/CentroDescargas/detalleArchivo?sec=12165736
A43: =IF($B43="","",ROW()-1) -> 42 | B43: IGN | C43: IGN-02 | D43: =IF($C43="","",IFERROR(VLOOKUP($C43,Map_Register!$A$2:$C$5,3,FALSE()),"")) -> Cultural Heritage Area | E43: Cultural | F43: 49261 | G43: Museo | H43: Museo Casa de Murillo | I43: Present | L43: symbolized as builing with emphasized red hue compared to surroundings | P43: https://centrodedescargas.cnig.es/CentroDescargas/detalleArchivo?sec=12165737
A44: =IF($B44="","",ROW()-1) -> 43 | B44: IGN | C44: IGN-02 | D44: =IF($C44="","",IFERROR(VLOOKUP($C44,Map_Register!$A$2:$C$5,3,FALSE()),"")) -> Cultural Heritage Area | E44: Cultural | F44: 49266 | G44: Museo | H44: Museo de Artes y Costumbres Populares de Sevilla | I44: Present | L44: museum symbolized as general building | P44: https://centrodedescargas.cnig.es/CentroDescargas/detalleArchivo?sec=12165738
A45: =IF($B45="","",ROW()-1) -> 44 | B45: IGN | C45: IGN-02 | D45: =IF($C45="","",IFERROR(VLOOKUP($C45,Map_Register!$A$2:$C$5,3,FALSE()),"")) -> Cultural Heritage Area | E45: Cultural | F45: 49268 | G45: Museo | H45: Museo Arqueológico de Sevilla | I45: Present (Emphasized) | L45: symbolized as building with brigh red hue compared to surroundings; with label | O45: Hue, Value | P45: https://centrodedescargas.cnig.es/CentroDescargas/detalleArchivo?sec=12165739
A46: =IF($B46="","",ROW()-1) -> 45 | B46: IGN | C46: IGN-02 | D46: =IF($C46="","",IFERROR(VLOOKUP($C46,Map_Register!$A$2:$C$5,3,FALSE()),"")) -> Cultural Heritage Area | E46: Cultural | F46: 49270 | G46: Museo | H46: Antiquarium | I46: Present | L46: symbolized as general building | P46: https://centrodedescargas.cnig.es/CentroDescargas/detalleArchivo?sec=12165740
A47: =IF($B47="","",ROW()-1) -> 46 | B47: IGN | C47: IGN-02 | D47: =IF($C47="","",IFERROR(VLOOKUP($C47,Map_Register!$A$2:$C$5,3,FALSE()),"")) -> Cultural Heritage Area | E47: Cultural | F47: 49271 | G47: Museo | H47: Museo Histórico Militar de Sevilla | I47: Present | L47: symbolized as general building | P47: https://centrodedescargas.cnig.es/CentroDescargas/detalleArchivo?sec=12165741
A48: =IF($B48="","",ROW()-1) -> 47 | B48: IGN | C48: IGN-02 | D48: =IF($C48="","",IFERROR(VLOOKUP($C48,Map_Register!$A$2:$C$5,3,FALSE()),"")) -> Cultural Heritage Area | E48: Cultural | F48: 49272 | G48: Museo | H48: Casa de la Ciencia | I48: Present | L48: symblized as general building | P48: https://centrodedescargas.cnig.es/CentroDescargas/detalleArchivo?sec=12165742
A49: =IF($B49="","",ROW()-1) -> 48 | B49: IGN | C49: IGN-02 | D49: =IF($C49="","",IFERROR(VLOOKUP($C49,Map_Register!$A$2:$C$5,3,FALSE()),"")) -> Cultural Heritage Area | E49: Cultural | F49: 49273 | G49: Museo | H49: Museo del Baile Flamenco | I49: Absent | J49: Yes | K49: Yes | L49: location falls on a generalized building rendered as general building ; but no indication of it being a museum | M49: No | P49: https://centrodedescargas.cnig.es/CentroDescargas/detalleArchivo?sec=12165743
A50: =IF($B50="","",ROW()-1) -> 49 | B50: IGN | C50: IGN-02 | D50: =IF($C50="","",IFERROR(VLOOKUP($C50,Map_Register!$A$2:$C$5,3,FALSE()),"")) -> Cultural Heritage Area | E50: Cultural | F50: 49278 | G50: Museo | H50: Centro Andaluz de Arte Contemporáneo | I50: Present | L50: symbolized as singular building ; red hue emphasized to surroundings | P50: https://centrodedescargas.cnig.es/CentroDescargas/detalleArchivo?sec=12165744
A51: =IF($B51="","",ROW()-1) -> 50 | B51: IGN | C51: IGN-02 | D51: =IF($C51="","",IFERROR(VLOOKUP($C51,Map_Register!$A$2:$C$5,3,FALSE()),"")) -> Cultural Heritage Area | E51: Cultural | F51: 49279 | G51: Museo | H51: Centro del Mudéjar | I51: Absent | J51: Yes | K51: Yes | L51: aggregated to building section | M51: No | P51: https://centrodedescargas.cnig.es/CentroDescargas/detalleArchivo?sec=12165745
A52: =IF($B52="","",ROW()-1) -> 51 | B52: IGN | C52: IGN-02 | D52: =IF($C52="","",IFERROR(VLOOKUP($C52,Map_Register!$A$2:$C$5,3,FALSE()),"")) -> Cultural Heritage Area | E52: Cultural | F52: 49284 | G52: Museo | H52: Museo de Bellas Artes de Sevilla | I52: Present | L52: singular building ; bright red hue | P52: https://centrodedescargas.cnig.es/CentroDescargas/detalleArchivo?sec=12165746
A53: =IF($B53="","",ROW()-1) -> 52 | B53: IGN | C53: IGN-02 | D53: =IF($C53="","",IFERROR(VLOOKUP($C53,Map_Register!$A$2:$C$5,3,FALSE()),"")) -> Cultural Heritage Area | E53: Cultural | F53: 49285 | G53: Museo | H53: CaixaForum Sevilla | I53: Present | L53: general building | P53: https://centrodedescargas.cnig.es/CentroDescargas/detalleArchivo?sec=12165747
A54: =IF($B54="","",ROW()-1) -> 53 | B54: IGN | C54: IGN-02 | D54: =IF($C54="","",IFERROR(VLOOKUP($C54,Map_Register!$A$2:$C$5,3,FALSE()),"")) -> Cultural Heritage Area | E54: Cultural | F54: 49286 | G54: Museo | H54: Museo Catedralicio | I54: Present (Emphasized) | L54: building with black outline and red hue emphasized to other surounding buildings | O54: Hue, Value | P54: https://centrodedescargas.cnig.es/CentroDescargas/detalleArchivo?sec=12165748
A55: =IF($B55="","",ROW()-1) -> 54 | B55: IGN | C55: IGN-02 | D55: =IF($C55="","",IFERROR(VLOOKUP($C55,Map_Register!$A$2:$C$5,3,FALSE()),"")) -> Cultural Heritage Area | E55: Cultural | F55: 49376 | G55: Muralla | H55: Murallas de Sevilla | I55: Present | L55: ancient wall | P55: https://centrodedescargas.cnig.es/CentroDescargas/detalleArchivo?sec=12165749
A56: =IF($B56="","",ROW()-1) -> 55 | B56: IGN | C56: IGN-02 | D56: =IF($C56="","",IFERROR(VLOOKUP($C56,Map_Register!$A$2:$C$5,3,FALSE()),"")) -> Cultural Heritage Area | E56: Cultural | F56: 49540 | G56: Centro cultural | H56: Centro Cívico Monasterio San Jerónimo | I56: Present | L56: singular building; red hue emphasized | P56: https://centrodedescargas.cnig.es/CentroDescargas/detalleArchivo?sec=12165750
A57: =IF($B57="","",ROW()-1) -> 56 | B57: IGN | C57: IGN-02 | D57: =IF($C57="","",IFERROR(VLOOKUP($C57,Map_Register!$A$2:$C$5,3,FALSE()),"")) -> Cultural Heritage Area | E57: Cultural | F57: 49553 | G57: Centro cultural | H57: Centro Cívico Blas Infante | I57: Present | L57: general building | P57: https://centrodedescargas.cnig.es/CentroDescargas/detalleArchivo?sec=12165751
A58: =IF($B58="","",ROW()-1) -> 57 | B58: IGN | C58: IGN-02 | D58: =IF($C58="","",IFERROR(VLOOKUP($C58,Map_Register!$A$2:$C$5,3,FALSE()),"")) -> Cultural Heritage Area | E58: Cultural | F58: 49554 | G58: Centro cultural | H58: Centro Cívico de Torreblanca | I58: Present | L58: general building | P58: https://centrodedescargas.cnig.es/CentroDescargas/detalleArchivo?sec=12165752
A59: =IF($B59="","",ROW()-1) -> 58 | B59: IGN | C59: IGN-02 | D59: =IF($C59="","",IFERROR(VLOOKUP($C59,Map_Register!$A$2:$C$5,3,FALSE()),"")) -> Cultural Heritage Area | E59: Cultural | F59: 49565 | G59: Centro cultural | H59: Centro Cívico de Olivares | I59: Present | L59: general building | P59: https://centrodedescargas.cnig.es/CentroDescargas/detalleArchivo?sec=12165753
A60: =IF($B60="","",ROW()-1) -> 59 | B60: IGN | C60: IGN-02 | D60: =IF($C60="","",IFERROR(VLOOKUP($C60,Map_Register!$A$2:$C$5,3,FALSE()),"")) -> Cultural Heritage Area | E60: Cultural | F60: 57015 | G60: Fortaleza/castillo | H60: Castillo de San Jorge#Castillo de la Inquisición | I60: Present | L60: general building | P60: https://centrodedescargas.cnig.es/CentroDescargas/detalleArchivo?sec=12165754
A61: =IF($B61="","",ROW()-1) -> 60 | B61: IGN | C61: IGN-02 | D61: =IF($C61="","",IFERROR(VLOOKUP($C61,Map_Register!$A$2:$C$5,3,FALSE()),"")) -> Cultural Heritage Area | E61: Cultural | F61: 57116 | G61: Muralla | H61: Murallas de Sevilla | I61: Present | L61: ancient wall | P61: https://centrodedescargas.cnig.es/CentroDescargas/detalleArchivo?sec=12165755
A62: =IF($B62="","",ROW()-1) -> 61 | B62: IGN | C62: IGN-02 | D62: =IF($C62="","",IFERROR(VLOOKUP($C62,Map_Register!$A$2:$C$5,3,FALSE()),"")) -> Cultural Heritage Area | E62: Cultural | F62: 57391 | G62: Muralla | H62: Murallas de Sevilla | I62: Absent | J62: Yes | K62: Yes | L62: close to other features | M62: No | P62: https://centrodedescargas.cnig.es/CentroDescargas/detalleArchivo?sec=12165756
A63: =IF($B63="","",ROW()-1) -> 62 | B63: IGN | C63: IGN-02 | D63: =IF($C63="","",IFERROR(VLOOKUP($C63,Map_Register!$A$2:$C$5,3,FALSE()),"")) -> Cultural Heritage Area | E63: Cultural | F63: 57633 | G63: Muralla | H63: Murallas de Sevilla | I63: Absent | J63: Yes | K63: Yes | L63: close to other features | M63: No | P63: https://centrodedescargas.cnig.es/CentroDescargas/detalleArchivo?sec=12165757
A64: =IF($B64="","",ROW()-1) -> 63 | B64: IGN | C64: IGN-02 | D64: =IF($C64="","",IFERROR(VLOOKUP($C64,Map_Register!$A$2:$C$5,3,FALSE()),"")) -> Cultural Heritage Area | E64: Cultural | F64: 64709 | G64: Centro cultural | H64: Fundación Tres Culturas | I64: Present | L64: general building | P64: https://centrodedescargas.cnig.es/CentroDescargas/detalleArchivo?sec=12165758
A65: =IF($B65="","",ROW()-1) -> 64 | B65: IGN | C65: IGN-02 | D65: =IF($C65="","",IFERROR(VLOOKUP($C65,Map_Register!$A$2:$C$5,3,FALSE()),"")) -> Cultural Heritage Area | E65: Cultural | F65: 64728 | G65: Monumento | H65: Estatua Hermanos Reyes | I65: Absent | J65: Yes | K65: Yes | L65: size | M65: No | P65: https://centrodedescargas.cnig.es/CentroDescargas/detalleArchivo?sec=12165759
A66: =IF($B66="","",ROW()-1) -> 65 | B66: IGN | C66: IGN-02 | D66: =IF($C66="","",IFERROR(VLOOKUP($C66,Map_Register!$A$2:$C$5,3,FALSE()),"")) -> Cultural Heritage Area | E66: Cultural | F66: 64819 | G66: Monumento | H66: Puerta de la Concepción | I66: Absent | J66: Yes | K66: Yes | L66: part of building | M66: No | P66: https://centrodedescargas.cnig.es/CentroDescargas/detalleArchivo?sec=12165760
A67: =IF($B67="","",ROW()-1) -> 66 | B67: IGN | C67: IGN-02 | D67: =IF($C67="","",IFERROR(VLOOKUP($C67,Map_Register!$A$2:$C$5,3,FALSE()),"")) -> Cultural Heritage Area | E67: Cultural | F67: 64843 | G67: Monumento | H67: Virgen de Belén | I67: Absent | J67: Yes | K67: Yes | L67: size | M67: No | P67: https://centrodedescargas.cnig.es/CentroDescargas/detalleArchivo?sec=12165761
A68: =IF($B68="","",ROW()-1) -> 67 | B68: IGN | C68: IGN-02 | D68: =IF($C68="","",IFERROR(VLOOKUP($C68,Map_Register!$A$2:$C$5,3,FALSE()),"")) -> Cultural Heritage Area | E68: Cultural | F68: 64854 | G68: Monumento | H68: Monumento a Gustavo Adolfo Bécquer | I68: Absent | J68: Yes | K68: Yes | L68: size | M68: No | P68: https://centrodedescargas.cnig.es/CentroDescargas/detalleArchivo?sec=12165762
A69: =IF($B69="","",ROW()-1) -> 68 | B69: IGN | C69: IGN-02 | D69: =IF($C69="","",IFERROR(VLOOKUP($C69,Map_Register!$A$2:$C$5,3,FALSE()),"")) -> Cultural Heritage Area | E69: Cultural | F69: 64855 | G69: Monumento | H69: Columnas Alameda de Hércules | I69: Absent | J69: Yes | K69: Yes | L69: size | M69: No | P69: https://centrodedescargas.cnig.es/CentroDescargas/detalleArchivo?sec=12165763
A70: =IF($B70="","",ROW()-1) -> 69 | B70: IGN | C70: IGN-02 | D70: =IF($C70="","",IFERROR(VLOOKUP($C70,Map_Register!$A$2:$C$5,3,FALSE()),"")) -> Cultural Heritage Area | E70: Cultural | F70: 64914 | G70: Museo | H70: Museo Marítimo de la Torre del Oro | I70: Present | L70: observation tower' | P70: https://centrodedescargas.cnig.es/CentroDescargas/detalleArchivo?sec=12165764
A71: =IF($B71="","",ROW()-1) -> 70 | B71: IGN | C71: IGN-02 | D71: =IF($C71="","",IFERROR(VLOOKUP($C71,Map_Register!$A$2:$C$5,3,FALSE()),"")) -> Cultural Heritage Area | E71: Cultural | F71: 64930 | G71: Monumento | H71: Monumento a la Tolerancia | I71: Absent | J71: Yes | K71: Yes | L71: size | M71: No | P71: https://centrodedescargas.cnig.es/CentroDescargas/detalleArchivo?sec=12165765
A72: =IF($B72="","",ROW()-1) -> 71 | B72: IGN | C72: IGN-02 | D72: =IF($C72="","",IFERROR(VLOOKUP($C72,Map_Register!$A$2:$C$5,3,FALSE()),"")) -> Cultural Heritage Area | E72: Cultural | F72: 64938 | G72: Monumento | H72: Monumento a María Auxiliadora | I72: Absent | J72: Yes | K72: Yes | L72: size | M72: No | P72: https://centrodedescargas.cnig.es/CentroDescargas/detalleArchivo?sec=12165766
A73: =IF($B73="","",ROW()-1) -> 72 | B73: IGN | C73: IGN-02 | D73: =IF($C73="","",IFERROR(VLOOKUP($C73,Map_Register!$A$2:$C$5,3,FALSE()),"")) -> Cultural Heritage Area | E73: Cultural | F73: 64962 | G73: Monumento | H73: Monumento a Juanito Valderrama | I73: Absent | J73: Yes | K73: Yes | L73: size | M73: No | P73: https://centrodedescargas.cnig.es/CentroDescargas/detalleArchivo?sec=12165767
A74: =IF($B74="","",ROW()-1) -> 73 | B74: IGN | C74: IGN-02 | D74: =IF($C74="","",IFERROR(VLOOKUP($C74,Map_Register!$A$2:$C$5,3,FALSE()),"")) -> Cultural Heritage Area | E74: Cultural | F74: 64968 | G74: Centro cultural | H74: Centro Cívico Entreparques | I74: Present | L74: general building | P74: https://centrodedescargas.cnig.es/CentroDescargas/detalleArchivo?sec=12165768
A75: =IF($B75="","",ROW()-1) -> 74 | B75: IGN | C75: IGN-02 | D75: =IF($C75="","",IFERROR(VLOOKUP($C75,Map_Register!$A$2:$C$5,3,FALSE()),"")) -> Cultural Heritage Area | E75: Cultural | F75: 64995 | G75: Monumento | H75: Pozo de la Arboledilla | I75: Absent | J75: Yes | K75: Yes | L75: size | M75: No | P75: https://centrodedescargas.cnig.es/CentroDescargas/detalleArchivo?sec=12165769
A76: =IF($B76="","",ROW()-1) -> 75 | B76: IGN | C76: IGN-02 | D76: =IF($C76="","",IFERROR(VLOOKUP($C76,Map_Register!$A$2:$C$5,3,FALSE()),"")) -> Cultural Heritage Area | E76: Cultural | F76: 65100 | G76: Restos arqueológicos | H76: Anfiteatro Romano de Itálica | I76: Present | L76: arch site | P76: https://centrodedescargas.cnig.es/CentroDescargas/detalleArchivo?sec=12165770
A77: =IF($B77="","",ROW()-1) -> 76 | B77: IGN | C77: IGN-02 | D77: =IF($C77="","",IFERROR(VLOOKUP($C77,Map_Register!$A$2:$C$5,3,FALSE()),"")) -> Cultural Heritage Area | E77: Cultural | F77: 65130 | G77: Monumento | H77: Monumento a Fray Bartolomé de las Casas | I77: Absent | J77: Yes | K77: Yes | L77: size | M77: No | P77: https://centrodedescargas.cnig.es/CentroDescargas/detalleArchivo?sec=12165771
A78: =IF($B78="","",ROW()-1) -> 77 | B78: IGN | C78: IGN-02 | D78: =IF($C78="","",IFERROR(VLOOKUP($C78,Map_Register!$A$2:$C$5,3,FALSE()),"")) -> Cultural Heritage Area | E78: Cultural | F78: 65136 | G78: Monumento | H78: Puerta del León | I78: Present | L78: general building; part of ancient/historical wall | P78: https://centrodedescargas.cnig.es/CentroDescargas/detalleArchivo?sec=12165772
A79: =IF($B79="","",ROW()-1) -> 78 | B79: IGN | C79: IGN-02 | D79: =IF($C79="","",IFERROR(VLOOKUP($C79,Map_Register!$A$2:$C$5,3,FALSE()),"")) -> Cultural Heritage Area | E79: Cultural | F79: 65190 | G79: Restos arqueológicos | H79: Templo de Trajano | I79: Present | L79: arch site | P79: https://centrodedescargas.cnig.es/CentroDescargas/detalleArchivo?sec=12165773
A80: =IF($B80="","",ROW()-1) -> 79 | B80: IGN | C80: IGN-02 | D80: =IF($C80="","",IFERROR(VLOOKUP($C80,Map_Register!$A$2:$C$5,3,FALSE()),"")) -> Cultural Heritage Area | E80: Cultural | F80: 65268 | G80: Monumento | H80: Monumento a San Juan Bosco | I80: Absent | J80: Yes | K80: Yes | L80: size | M80: No | P80: https://centrodedescargas.cnig.es/CentroDescargas/detalleArchivo?sec=12165774
A81: =IF($B81="","",ROW()-1) -> 80 | B81: IGN | C81: IGN-02 | D81: =IF($C81="","",IFERROR(VLOOKUP($C81,Map_Register!$A$2:$C$5,3,FALSE()),"")) -> Cultural Heritage Area | E81: Cultural | F81: 65274 | G81: Monumento | H81: Glorieta Olímpica | I81: Absent | J81: Yes | K81: Yes | L81: size, no monument symbol | M81: No | P81: https://centrodedescargas.cnig.es/CentroDescargas/detalleArchivo?sec=12165775
A82: =IF($B82="","",ROW()-1) -> 81 | B82: IGN | C82: IGN-02 | D82: =IF($C82="","",IFERROR(VLOOKUP($C82,Map_Register!$A$2:$C$5,3,FALSE()),"")) -> Cultural Heritage Area | E82: Cultural | F82: 65333 | G82: Monumento | H82: Caídos por España | I82: Absent | J82: Yes | K82: Yes | L82: size | M82: No | P82: https://centrodedescargas.cnig.es/CentroDescargas/detalleArchivo?sec=12165776
A83: =IF($B83="","",ROW()-1) -> 82 | B83: IGN | C83: IGN-02 | D83: =IF($C83="","",IFERROR(VLOOKUP($C83,Map_Register!$A$2:$C$5,3,FALSE()),"")) -> Cultural Heritage Area | E83: Cultural | F83: 65337 | G83: Monumento | H83: Avión Azor | I83: Absent | J83: Yes | K83: Yes | L83: size | M83: No | P83: https://centrodedescargas.cnig.es/CentroDescargas/detalleArchivo?sec=12165777
A84: =IF($B84="","",ROW()-1) -> 83 | B84: IGN | C84: IGN-02 | D84: =IF($C84="","",IFERROR(VLOOKUP($C84,Map_Register!$A$2:$C$5,3,FALSE()),"")) -> Cultural Heritage Area | E84: Cultural | F84: 65371 | G84: Monumento | H84: Arco de la Plata o de Mañara | I84: Present | L84: observation tower | P84: https://centrodedescargas.cnig.es/CentroDescargas/detalleArchivo?sec=12165778
A85: =IF($B85="","",ROW()-1) -> 84 | B85: IGN | C85: IGN-02 | D85: =IF($C85="","",IFERROR(VLOOKUP($C85,Map_Register!$A$2:$C$5,3,FALSE()),"")) -> Cultural Heritage Area | E85: Cultural | F85: 65412 | G85: Monumento | H85: Estatua del Torero Juan Antonio Ruiz Espartaco | I85: Absent | J85: Yes | K85: Yes | L85: size | M85: No | P85: https://centrodedescargas.cnig.es/CentroDescargas/detalleArchivo?sec=12165779
A86: =IF($B86="","",ROW()-1) -> 85 | B86: IGN | C86: IGN-02 | D86: =IF($C86="","",IFERROR(VLOOKUP($C86,Map_Register!$A$2:$C$5,3,FALSE()),"")) -> Cultural Heritage Area | E86: Cultural | F86: 65487 | G86: Monumento | H86: Monumento a la Virgen de Cuatrovitas | I86: Absent | J86: Yes | K86: Yes | L86: size | M86: No | P86: https://centrodedescargas.cnig.es/CentroDescargas/detalleArchivo?sec=12165780
A87: =IF($B87="","",ROW()-1) -> 86 | B87: IGN | C87: IGN-02 | D87: =IF($C87="","",IFERROR(VLOOKUP($C87,Map_Register!$A$2:$C$5,3,FALSE()),"")) -> Cultural Heritage Area | E87: Cultural | F87: 65490 | G87: Monumento | H87: Monumento a Pepe Luis Vázquez | I87: Absent | J87: Yes | K87: Yes | L87: size | M87: No | P87: https://centrodedescargas.cnig.es/CentroDescargas/detalleArchivo?sec=12165781
A88: =IF($B88="","",ROW()-1) -> 87 | B88: IGN | C88: IGN-02 | D88: =IF($C88="","",IFERROR(VLOOKUP($C88,Map_Register!$A$2:$C$5,3,FALSE()),"")) -> Cultural Heritage Area | E88: Cultural | F88: 65496 | G88: Monumento | H88: Monumento a Don Juan Tenorio | I88: Absent | J88: Yes | K88: Yes | L88: size | M88: No | P88: https://centrodedescargas.cnig.es/CentroDescargas/detalleArchivo?sec=12165782
A89: =IF($B89="","",ROW()-1) -> 88 | B89: IGN | C89: IGN-02 | D89: =IF($C89="","",IFERROR(VLOOKUP($C89,Map_Register!$A$2:$C$5,3,FALSE()),"")) -> Cultural Heritage Area | E89: Cultural | F89: 65531 | G89: Monumento | H89: Monumento a Rodrigo de Triana | I89: Absent | J89: Yes | K89: Yes | L89: size | M89: No | P89: https://centrodedescargas.cnig.es/CentroDescargas/detalleArchivo?sec=12165783
A90: =IF($B90="","",ROW()-1) -> 89 | B90: IGN | C90: IGN-02 | D90: =IF($C90="","",IFERROR(VLOOKUP($C90,Map_Register!$A$2:$C$5,3,FALSE()),"")) -> Cultural Heritage Area | E90: Cultural | F90: 65544 | G90: Museo | H90: Museo de La Rinconada, Colecciones Arqueológicas y Paleontológicas en memoria de Francisco Sousa | I90: Present | L90: general building | P90: https://centrodedescargas.cnig.es/CentroDescargas/detalleArchivo?sec=12165784
A91: =IF($B91="","",ROW()-1) -> 90 | B91: IGN | C91: IGN-02 | D91: =IF($C91="","",IFERROR(VLOOKUP($C91,Map_Register!$A$2:$C$5,3,FALSE()),"")) -> Cultural Heritage Area | E91: Cultural | F91: 65596 | G91: Restos arqueológicos | H91: Casa de los Pájaros | I91: Present | L91: arch site | P91: https://centrodedescargas.cnig.es/CentroDescargas/detalleArchivo?sec=12165785
A92: =IF($B92="","",ROW()-1) -> 91 | B92: IGN | C92: IGN-02 | D92: =IF($C92="","",IFERROR(VLOOKUP($C92,Map_Register!$A$2:$C$5,3,FALSE()),"")) -> Cultural Heritage Area | E92: Cultural | F92: 65623 | G92: Monumento | H92: Monumento al Toreo | I92: Present | L92: monument symbolized as an arena | P92: https://centrodedescargas.cnig.es/CentroDescargas/detalleArchivo?sec=12165786
A93: =IF($B93="","",ROW()-1) -> 92 | B93: IGN | C93: IGN-02 | D93: =IF($C93="","",IFERROR(VLOOKUP($C93,Map_Register!$A$2:$C$5,3,FALSE()),"")) -> Cultural Heritage Area | E93: Cultural | F93: 65667 | G93: Monumento | H93: Monumento a Colón#El Huevo de Colón | I93: Absent | J93: Yes | K93: Yes | L93: size | M93: No | P93: https://centrodedescargas.cnig.es/CentroDescargas/detalleArchivo?sec=12165787
A94: =IF($B94="","",ROW()-1) -> 93 | B94: IGN | C94: IGN-02 | D94: =IF($C94="","",IFERROR(VLOOKUP($C94,Map_Register!$A$2:$C$5,3,FALSE()),"")) -> Cultural Heritage Area | E94: Cultural | F94: 65688 | G94: Monumento | H94: Monumento a la alfarería y la soleá | I94: Absent | J94: Yes | K94: Yes | L94: size | M94: No | P94: https://centrodedescargas.cnig.es/CentroDescargas/detalleArchivo?sec=12165788
A95: =IF($B95="","",ROW()-1) -> 94 | B95: IGN | C95: IGN-02 | D95: =IF($C95="","",IFERROR(VLOOKUP($C95,Map_Register!$A$2:$C$5,3,FALSE()),"")) -> Cultural Heritage Area | E95: Cultural | F95: 65761 | G95: Centro cultural | H95: Centro Cultural de la Villa | I95: Present | L95: general building | P95: https://centrodedescargas.cnig.es/CentroDescargas/detalleArchivo?sec=12165789
A96: =IF($B96="","",ROW()-1) -> 95 | B96: IGN | C96: IGN-02 | D96: =IF($C96="","",IFERROR(VLOOKUP($C96,Map_Register!$A$2:$C$5,3,FALSE()),"")) -> Cultural Heritage Area | E96: Cultural | F96: 65799 | G96: Monumento | H96: Puerta de la Macarena | I96: Present | L96: part of historical/ancient wall; singular building ; red hue; no label | O96: Hue | P96: https://centrodedescargas.cnig.es/CentroDescargas/detalleArchivo?sec=12165790
A97: =IF($B97="","",ROW()-1) -> 96 | B97: IGN | C97: IGN-02 | D97: =IF($C97="","",IFERROR(VLOOKUP($C97,Map_Register!$A$2:$C$5,3,FALSE()),"")) -> Cultural Heritage Area | E97: Cultural | F97: 65809 | G97: Monumento | H97: Monumento a la Constitución de 1978 | I97: Absent | J97: Yes | K97: Yes | L97: size | M97: No | P97: https://centrodedescargas.cnig.es/CentroDescargas/detalleArchivo?sec=12165791
A98: =IF($B98="","",ROW()-1) -> 97 | B98: IGN | C98: IGN-02 | D98: =IF($C98="","",IFERROR(VLOOKUP($C98,Map_Register!$A$2:$C$5,3,FALSE()),"")) -> Cultural Heritage Area | E98: Cultural | F98: 65830 | G98: Monumento | H98: Estatua a la Torta de Aceite | I98: Absent | J98: Yes | K98: Yes | L98: size | M98: No | P98: https://centrodedescargas.cnig.es/CentroDescargas/detalleArchivo?sec=12165792
A99: =IF($B99="","",ROW()-1) -> 98 | B99: IGN | C99: IGN-02 | D99: =IF($C99="","",IFERROR(VLOOKUP($C99,Map_Register!$A$2:$C$5,3,FALSE()),"")) -> Cultural Heritage Area | E99: Cultural | F99: 65844 | G99: Monumento | H99: Monumento a Trajano | I99: Absent | J99: Yes | K99: Yes | L99: size | M99: No | P99: https://centrodedescargas.cnig.es/CentroDescargas/detalleArchivo?sec=12165793
A100: =IF($B100="","",ROW()-1) -> 99 | B100: IGN | C100: IGN-02 | D100: =IF($C100="","",IFERROR(VLOOKUP($C100,Map_Register!$A$2:$C$5,3,FALSE()),"")) -> Cultural Heritage Area | E100: Cultural | F100: 65853 | G100: Monumento | H100: Escudo de Castilleja de la Cuesta | I100: Absent | J100: Yes | K100: Yes | L100: size | M100: No | P100: https://centrodedescargas.cnig.es/CentroDescargas/detalleArchivo?sec=12165794
...

Sheet Summary
A1: Spain Representation Inventory — Summary of Coding Results
A2: National Mapping Agency: IGN | Auto-summarized from the Coding_Records sheets (Table 7 instrument, Section 3.5). Figures recalculate automatically as records are added.
A3: Note: 'Present' totals include emphasized features (Code beginning "Present"); 'Absent' totals include minor spelling/case variants (Code beginning "Absent"); 'Other/Unclear' captures any remaining codes (e.g. "outside sheet extent").
A5: 1. Overall Coding Results by Category
A6: Category | B6: Total Records | C6: Present | D6: Present (Emphasized) | E6: Absent | F6: Other / Unclear | G6: % Present | H6: % Absent
A7: Culture | B7: =COUNTA(Spain_Culture!I2:I503) -> 249 | C7: =COUNTIF(Spain_Culture!I2:I503,"Present*")-COUNTIF(Spain_Culture!I2:I503,"*Emphasi*") -> 89 | D7: =COUNTIF(Spain_Culture!I2:I503,"*Emphasi*") -> 12 | E7: =COUNTIF(Spain_Culture!I2:I503,"Absent*") -> 145 | F7: =B7-C7-D7-E7 -> 3 | G7: =IF(B7=0,0,(C7+D7)/B7) -> 0.40562249 | H7: =IF(B7=0,0,E7/B7) -> 0.58232932
A8: Border | B8: =COUNTA(Spain_Border!H2:H61) -> 60 | C8: =COUNTIF(Spain_Border!H2:H61,"Present*")-COUNTIF(Spain_Border!H2:H61,"*Emphasi*") -> 52 | D8: =COUNTIF(Spain_Border!H2:H61,"*Emphasi*") -> 1 | E8: =COUNTIF(Spain_Border!H2:H61,"Absent*") -> 7 | F8: =B8-C8-D8-E8 -> 0 | G8: =IF(B8=0,0,(C8+D8)/B8) -> 0.88333333 | H8: =IF(B8=0,0,E8/B8) -> 0.11666667
A9: Military | B9: =COUNTA(Spain_Military!H2:H9) -> 8 | C9: =COUNTIF(Spain_Military!H2:H9,"Present*")-COUNTIF(Spain_Military!H2:H9,"*Emphasi*") -> 5 | D9: =COUNTIF(Spain_Military!H2:H9,"*Emphasi*") -> 0 | E9: =COUNTIF(Spain_Military!H2:H9,"Absent*") -> 3 | F9: =B9-C9-D9-E9 -> 0 | G9: =IF(B9=0,0,(C9+D9)/B9) -> 0.625 | H9: =IF(B9=0,0,E9/B9) -> 0.375
A10: Toponym | B10: =COUNTA(Spain_Toponym!J2:J1833) -> 1832 | C10: =COUNTIF(Spain_Toponym!J2:J1833,"Present*")-COUNTIF(Spain_Toponym!J2:J1833,"*Emphasi*") -> 1075 | D10: =COUNTIF(Spain_Toponym!J2:J1833,"*Emphasi*") -> 64 | E10: =COUNTIF(Spain_Toponym!J2:J1833,"Absent*") -> 693 | F10: =B10-C10-D10-E10 -> 0 | G10: =IF(B10=0,0,(C10+D10)/B10) -> 0.62172489 | H10: =IF(B10=0,0,E10/B10) -> 0.37827511
A11: TOTAL | B11: =SUM(B7:B10) -> 2149 | C11: =SUM(C7:C10) -> 1221 | D11: =SUM(D7:D10) -> 77 | E11: =SUM(E7:E10) -> 848 | G11: =IF(B11=0,0,(C11+D11)/B11) -> 0.60400186 | H11: =IF(B11=0,0,E11/B11) -> 0.39460214
A13: 2. Visual Emphasis Analysis (share of Present features that are emphasized)
A14: Category | B14: Present (Total, incl. emphasized) | C14: Present (Emphasized) | D14: % of Present Emphasized
A15: Culture | B15: =C7+D7 -> 101 | C15: =D7 -> 12 | D15: =IF(B15=0,0,C15/B15) -> 0.11881188
A16: Border | B16: =C8+D8 -> 53 | C16: =D8 -> 1 | D16: =IF(B16=0,0,C16/B16) -> 0.018867925
A17: Military | B17: =C9+D9 -> 5 | C17: =D9 -> 0 | D17: =IF(B17=0,0,C17/B17) -> 0
A18: Toponym | B18: =C10+D10 -> 1139 | C18: =D10 -> 64 | D18: =IF(B18=0,0,C18/B18) -> 0.05618964
A19: TOTAL | B19: =SUM(B15:B18) -> 1298 | C19: =SUM(C15:C18) -> 77 | D19: =IF(B19=0,0,C19/B19) -> 0.059322034
A21: 3. Absence-Reason Flag Analysis (basis coded for Absent features)
A22: Category | B22: Absent Total | C22: Rendering-Stage Omission (Yes) | D22: Specification Gap (Yes) | E22: Generalization- Attributed (Yes)
A23: Culture | B23: =E7 -> 145 | C23: =COUNTIF(Spain_Culture!J2:J503,"*Yes*") -> 144 | D23: =COUNTIF(Spain_Culture!M2:M503,"*Yes*") -> 0 | E23: =COUNTIF(Spain_Culture!K2:K503,"*Yes*") -> 139
A24: Border | B24: =E8 -> 7 | C24: =COUNTIF(Spain_Border!I2:I61,"*Yes*") -> 5 | D24: =COUNTIF(Spain_Border!L2:L61,"*Yes*") -> 1 | E24: =COUNTIF(Spain_Border!J2:J61,"*Yes*") -> 6
A25: Military | B25: =E9 -> 3 | C25: =COUNTIF(Spain_Military!I2:I9,"*Yes*") -> 0 | D25: =COUNTIF(Spain_Military!L2:L9,"*Yes*") -> 3 | E25: =COUNTIF(Spain_Military!J2:J9,"*Yes*") -> 0
A26: Toponym | B26: =E10 -> 693 | C26: =COUNTIF(Spain_Toponym!K2:K1833,"*Yes*") -> 691 | D26: =COUNTIF(Spain_Toponym!N2:N1833,"*Yes*") -> 0 | E26: =COUNTIF(Spain_Toponym!L2:L1833,"*Yes*") -> 311
A27: TOTAL | B27: =SUM(B23:B26) -> 848 | C27: =SUM(C23:C26) -> 840 | D27: =SUM(D23:D26) -> 4 | E27: =SUM(E23:E26) -> 456
A29: Note: a record may carry more than one flag, so flag counts need not sum to the Absent total; N/A and blank entries are excluded from these counts.
A31: 4. Coding Coverage by Map Sample
A32: Map ID | B32: Area / Context | C32: Sheet Type | D32: Total Records | E32: Present | F32: Absent | G32: % Absent
A33: =Map_Register!A2 -> IGN-01 | B33: =Map_Register!D2 -> Campo de Gibraltar (contested international boundary) | C33: =Map_Register!C2 -> Border Region | D33: =COUNTIF(Spain_Culture!$C$2:$C$503,$A33)+COUNTIF(Spain_Border!$C$2:$C$61,$A33)+COUNTIF(Spain_Military!$C$2:$C$9,$A33)+COUNTIF(Spain_Toponym!$C$2:$C$1833,$A33) -> 93 | E33: =COUNTIFS(Spain_Culture!$C$2:$C$503,$A33,Spain_Culture!$I$2:$I$503,"Present*")+COUNTIFS(Spain_Border!$C$2:$C$61,$A33,Spain_Border!$H$2:$H$61,"Present*")+COUNTIFS(Spain_Military!$C$2:$C$9,$A33,Spain_Military!$H$2:$H$9,"Present*")+COUNTIFS(Spain_Toponym!$C$2:$C$1833,$A33,Spain_Toponym!$J$2:$J$1833,"Present*") -> 65 | F33: =COUNTIFS(Spain_Culture!$C$2:$C$503,$A33,Spain_Culture!$I$2:$I$503,"Absent*")+COUNTIFS(Spain_Border!$C$2:$C$61,$A33,Spain_Border!$H$2:$H$61,"Absent*")+COUNTIFS(Spain_Military!$C$2:$C$9,$A33,Spain_Military!$H$2:$H$9,"Absent*")+COUNTIFS(Spain_Toponym!$C$2:$C$1833,$A33,Spain_Toponym!$J$2:$J$1833,"Absent*") -> 28 | G33: =IF(D33=0,0,F33/D33) -> 0.30107527
A34: =Map_Register!A3 -> IGN-02 | B34: =Map_Register!D3 -> Sevilla region (Cathedral, Alcázar, Archivo de Indias UNESCO WHS) | C34: =Map_Register!C3 -> Cultural Heritage Area | D34: =COUNTIF(Spain_Culture!$C$2:$C$503,$A34)+COUNTIF(Spain_Border!$C$2:$C$61,$A34)+COUNTIF(Spain_Military!$C$2:$C$9,$A34)+COUNTIF(Spain_Toponym!$C$2:$C$1833,$A34) -> 761 | E34: =COUNTIFS(Spain_Culture!$C$2:$C$503,$A34,Spain_Culture!$I$2:$I$503,"Present*")+COUNTIFS(Spain_Border!$C$2:$C$61,$A34,Spain_Border!$H$2:$H$61,"Present*")+COUNTIFS(Spain_Military!$C$2:$C$9,$A34,Spain_Military!$H$2:$H$9,"Present*")+COUNTIFS(Spain_Toponym!$C$2:$C$1833,$A34,Spain_Toponym!$J$2:$J$1833,"Present*") -> 410 | F34: =COUNTIFS(Spain_Culture!$C$2:$C$503,$A34,Spain_Culture!$I$2:$I$503,"Absent*")+COUNTIFS(Spain_Border!$C$2:$C$61,$A34,Spain_Border!$H$2:$H$61,"Absent*")+COUNTIFS(Spain_Military!$C$2:$C$9,$A34,Spain_Military!$H$2:$H$9,"Absent*")+COUNTIFS(Spain_Toponym!$C$2:$C$1833,$A34,Spain_Toponym!$J$2:$J$1833,"Absent*") -> 351 | G34: =IF(D34=0,0,F34/D34) -> 0.46123522
A35: =Map_Register!A4 -> IGN-03 | B35: =Map_Register!D4 -> Cádiz, Andalusia | C35: =Map_Register!C4 -> Military Zone | D35: =COUNTIF(Spain_Culture!$C$2:$C$503,$A35)+COUNTIF(Spain_Border!$C$2:$C$61,$A35)+COUNTIF(Spain_Military!$C$2:$C$9,$A35)+COUNTIF(Spain_Toponym!$C$2:$C$1833,$A35) -> 245 | E35: =COUNTIFS(Spain_Culture!$C$2:$C$503,$A35,Spain_Culture!$I$2:$I$503,"Present*")+COUNTIFS(Spain_Border!$C$2:$C$61,$A35,Spain_Border!$H$2:$H$61,"Present*")+COUNTIFS(Spain_Military!$C$2:$C$9,$A35,Spain_Military!$H$2:$H$9,"Present*")+COUNTIFS(Spain_Toponym!$C$2:$C$1833,$A35,Spain_Toponym!$J$2:$J$1833,"Present*") -> 159 | F35: =COUNTIFS(Spain_Culture!$C$2:$C$503,$A35,Spain_Culture!$I$2:$I$503,"Absent*")+COUNTIFS(Spain_Border!$C$2:$C$61,$A35,Spain_Border!$H$2:$H$61,"Absent*")+COUNTIFS(Spain_Military!$C$2:$C$9,$A35,Spain_Military!$H$2:$H$9,"Absent*")+COUNTIFS(Spain_Toponym!$C$2:$C$1833,$A35,Spain_Toponym!$J$2:$J$1833,"Absent*") -> 83 | G35: =IF(D35=0,0,F35/D35) -> 0.33877551
A36: =Map_Register!A5 -> IGN-04 | B36: =Map_Register!D5 -> Navarra / Gipuzkoa Region | C36: =Map_Register!C5 -> Toponym Labels | D36: =COUNTIF(Spain_Culture!$C$2:$C$503,$A36)+COUNTIF(Spain_Border!$C$2:$C$61,$A36)+COUNTIF(Spain_Military!$C$2:$C$9,$A36)+COUNTIF(Spain_Toponym!$C$2:$C$1833,$A36) -> 1050 | E36: =COUNTIFS(Spain_Culture!$C$2:$C$503,$A36,Spain_Culture!$I$2:$I$503,"Present*")+COUNTIFS(Spain_Border!$C$2:$C$61,$A36,Spain_Border!$H$2:$H$61,"Present*")+COUNTIFS(Spain_Military!$C$2:$C$9,$A36,Spain_Military!$H$2:$H$9,"Present*")+COUNTIFS(Spain_Toponym!$C$2:$C$1833,$A36,Spain_Toponym!$J$2:$J$1833,"Present*") -> 664 | F36: =COUNTIFS(Spain_Culture!$C$2:$C$503,$A36,Spain_Culture!$I$2:$I$503,"Absent*")+COUNTIFS(Spain_Border!$C$2:$C$61,$A36,Spain_Border!$H$2:$H$61,"Absent*")+COUNTIFS(Spain_Military!$C$2:$C$9,$A36,Spain_Military!$H$2:$H$9,"Absent*")+COUNTIFS(Spain_Toponym!$C$2:$C$1833,$A36,Spain_Toponym!$J$2:$J$1833,"Absent*") -> 386 | G36: =IF(D36=0,0,F36/D36) -> 0.36761905
A37: TOTAL | D37: =SUM(D33:D36) -> 2149 | E37: =SUM(E33:E36) -> 1298 | F37: =SUM(F33:F36) -> 848 | G37: =IF(D37=0,0,F37/D37) -> 0.39460214
A39: Headline Figures
A40: Total coded features (all categories) | F40: =B11 -> 2149
A41: Overall % Present (incl. emphasized) | F41: =G11 -> 0.60400186
A42: Overall % Absent | F42: =H11 -> 0.39460214
A43: Overall % of Present features visually emphasized | F43: =IF((C11+D11)=0,0,D11/(C11+D11)) -> 0.059322034

Sheet Lists
A1: NMA | B1: Category | C1: Code | D1: RenderingStage_Flag | E1: YN | F1: Bertin_Variable | G1: Sheet_Type
A2: BEV | B2: Military | C2: Absent | D2: Y | E2: Y | F2: Size | G2: Border Region
A3: NLS-FI | B3: Border | C3: Present | D3: N/A | E3: N | F3: Value | G3: Cultural Heritage Area
A4: IGN | B4: Cultural | C4: Present (Emphasized) | F4: Color | G4: Military Zone
B5: Toponym | C5: Present (De-emphasized) | F5: Typographic weight | G5: Toponym Labels
C6: Present (Differentiated) | F6: Position | G6: Control / Ordinary Area
F7: Line style
F8: N/A
